{
  "documents": [
    {
      "text": "FACULTAD: FACULTAD_DE_CIENCIAS_AGRARIAS\nCOORDINADOR: Betsy Zelmira Avalos Alejo\nEMAIL: fca.ui@unap.edu.pe\nTELÉFONO: 962382228\nHORARIO: 7:30 a 14:00 horas\nUBICACIÓN: Pabellón antiguo de la E. P. Ing. Agronómica, Segundo Piso, Oficina 206, Ciudad Universitaria\nATENCIÓN: Lunes a viernes de 7:30 a 14:00 h\nALIAS: Ciencias Agrarias, FCA, Agronomía, Agrarias\n\nINFORMACIÓN COMPLETA:\nTIPO: coordinador NOMBRE: Betsy Zelmira Avalos Alejo EMAIL: fca.ui@unap.edu.pe TELEFONO: 962382228 HORARIO: 7:30 a 14:00 horas ATENCION: Lunes a viernes de 7:30 a 14:00 h UBICACION: Pabellón antiguo de la E. P. Ing. Agronómica, Segundo Piso, Oficina 206, Ciudad Universitaria ALIAS: Ciencias Agrarias, FCA, Agronomía, Agrarias",
      "source": "coordinadores",
      "type": "coordinador",
      "facultad": "FACULTAD_DE_CIENCIAS_AGRARIAS",
      "entidad": "facultad",
      "metadata": {
        "tipo": "coordinador",
        "nombre": "Betsy Zelmira Avalos Alejo",
        "email": "fca.ui@unap.edu.pe",
        "telefono": "962382228",
        "horario": "7:30 a 14:00 horas",
        "atencion": "Lunes a viernes de 7:30 a 14:00 h",
        "ubicacion": "Pabellón antiguo de la E. P. Ing. Agronómica, Segundo Piso, Oficina 206, Ciudad Universitaria",
        "alias": "Ciencias Agrarias, FCA, Agronomía, Agrarias"
      }
    },
    {
      "text": "FACULTAD: FACULTAD_DE_MEDICINA_VETERINARIA_Y_ZOOTECNIA\nCOORDINADOR: Elizabeth Choque Sallo\nEMAIL: investigacion.fmvz@unap.edu.pe\nTELÉFONO: 951644391\nHORARIO: 8:00 a 13:00 horas\nUBICACIÓN: Pabellón antiguo de la E.P. Medicina Veterinaria, Segundo Piso, Oficina 106, Ciudad Universitaria\nATENCIÓN: Lunes a viernes de 8:00 a 13:00 h\nALIAS: Medicina Veterinaria, Veterinaria, Zootecnia, FMVZ\n\nINFORMACIÓN COMPLETA:\nTIPO: coordinador NOMBRE: Elizabeth Choque Sallo EMAIL: investigacion.fmvz@unap.edu.pe TELEFONO: 951644391 HORARIO: 8:00 a 13:00 horas ATENCION: Lunes a viernes de 8:00 a 13:00 h UBICACION: Pabellón antiguo de la E.P. Medicina Veterinaria, Segundo Piso, Oficina 106, Ciudad Universitaria ALIAS: Medicina Veterinaria, Veterinaria, Zootecnia, FMVZ",
      "source": "coordinadores",
      "type": "coordinador",
      "facultad": "FACULTAD_DE_MEDICINA_VETERINARIA_Y_ZOOTECNIA",
      "entidad": "facultad",
      "metadata": {
        "tipo": "coordinador",
        "nombre": "Elizabeth Choque Sallo",
        "email": "investigacion.fmvz@unap.edu.pe",
        "telefono": "951644391",
        "horario": "8:00 a 13:00 horas",
        "atencion": "Lunes a viernes de 8:00 a 13:00 h",
        "ubicacion": "Pabellón antiguo de la E.P. Medicina Veterinaria, Segundo Piso, Oficina 106, Ciudad Universitaria",
        "alias": "Medicina Veterinaria, Veterinaria, Zootecnia, FMVZ"
      }
    },
    {
      "text": "FACULTAD: FACULTAD_DE_INGENIERIA_ECONOMICA\nCOORDINADOR: Delia Aguilar Laura\nEMAIL: unidadinvestigacion.fie@unap.edu.pe\nTELÉFONO: 951074978\nHORARIO: 8:00 a 13:00 horas\nUBICACIÓN: Pabellón nuevo de E.P. Ingeniería Económica, Cuarto Piso, Ciudad Universitaria\nATENCIÓN: Lunes a viernes de 8:00 a 13:00 h\nALIAS: Ingeniería Económica, FIE, Economía, Económica\n\nINFORMACIÓN COMPLETA:\nTIPO: coordinador NOMBRE: Delia Aguilar Laura EMAIL: unidadinvestigacion.fie@unap.edu.pe TELEFONO: 951074978 HORARIO: 8:00 a 13:00 horas ATENCION: Lunes a viernes de 8:00 a 13:00 h UBICACION: Pabellón nuevo de E.P. Ingeniería Económica, Cuarto Piso, Ciudad Universitaria ALIAS: Ingeniería Económica, FIE, Economía, Económica",
      "source": "coordinadores",
      "type": "coordinador",
      "facultad": "FACULTAD_DE_INGENIERIA_ECONOMICA",
      "entidad": "facultad",
      "metadata": {
        "tipo": "coordinador",
        "nombre": "Delia Aguilar Laura",
        "email": "unidadinvestigacion.fie@unap.edu.pe",
        "telefono": "951074978",
        "horario": "8:00 a 13:00 horas",
        "atencion": "Lunes a viernes de 8:00 a 13:00 h",
        "ubicacion": "Pabellón nuevo de E.P. Ingeniería Económica, Cuarto Piso, Ciudad Universitaria",
        "alias": "Ingeniería Económica, FIE, Economía, Económica"
      }
    },
    {
      "text": "FACULTAD: FACULTAD_DE_CIENCIAS_CONTABLES_Y_ADMINISTRATIVAS\nCOORDINADOR: Massiel Gonzales Condori\nEMAIL: duifcca@unap.edu.pe\nTELÉFONO: 925306963\nHORARIO: 8:00 a 14:00 horas\nUBICACIÓN: Pabellón Antiguo E.P. Contabilidad, Tercer piso, Ciudad Universitaria\nATENCIÓN: Lunes a viernes de 8:00 a 14:00 h\nALIAS: Contables y Administrativas, FCCA, Contabilidad, Administración\n\nINFORMACIÓN COMPLETA:\nTIPO: coordinador NOMBRE: Massiel Gonzales Condori EMAIL: duifcca@unap.edu.pe TELEFONO: 925306963 HORARIO: 8:00 a 14:00 horas ATENCION: Lunes a viernes de 8:00 a 14:00 h UBICACION: Pabellón Antiguo E.P. Contabilidad, Tercer piso, Ciudad Universitaria ALIAS: Contables y Administrativas, FCCA, Contabilidad, Administración",
      "source": "coordinadores",
      "type": "coordinador",
      "facultad": "FACULTAD_DE_CIENCIAS_CONTABLES_Y_ADMINISTRATIVAS",
      "entidad": "facultad",
      "metadata": {
        "tipo": "coordinador",
        "nombre": "Massiel Gonzales Condori",
        "email": "duifcca@unap.edu.pe",
        "telefono": "925306963",
        "horario": "8:00 a 14:00 horas",
        "atencion": "Lunes a viernes de 8:00 a 14:00 h",
        "ubicacion": "Pabellón Antiguo E.P. Contabilidad, Tercer piso, Ciudad Universitaria",
        "alias": "Contables y Administrativas, FCCA, Contabilidad, Administración"
      }
    },
    {
      "text": "FACULTAD: FACULTAD_DE_TRABAJO_SOCIAL\nCOORDINADOR: Jhonatan Edward Charca Noblega\nEMAIL: investigacion.fts@unap.edu.pe\nTELÉFONO: 989655958\nHORARIO: 8:00 a 13:00 horas\nUBICACIÓN: Pabellón antiguo de E.P. de Trabajo Social, Segundo Piso, Oficina 205, Ciudad Universitaria\nATENCIÓN: Lunes a viernes de 8:00 a 13:00 h\nALIAS: Trabajo Social, FTS, Servicio Social\n\nINFORMACIÓN COMPLETA:\nTIPO: coordinador NOMBRE: Jhonatan Edward Charca Noblega EMAIL: investigacion.fts@unap.edu.pe EMAIL_ALTERNATIVO: jcharca@unap.edu.pe TELEFONO: 989655958 HORARIO: 8:00 a 13:00 horas ATENCION: Lunes a viernes de 8:00 a 13:00 h UBICACION: Pabellón antiguo de E.P. de Trabajo Social, Segundo Piso, Oficina 205, Ciudad Universitaria ALIAS: Trabajo Social, FTS, Servicio Social",
      "source": "coordinadores",
      "type": "coordinador",
      "facultad": "FACULTAD_DE_TRABAJO_SOCIAL",
      "entidad": "facultad",
      "metadata": {
        "tipo": "coordinador",
        "nombre": "Jhonatan Edward Charca Noblega",
        "email": "investigacion.fts@unap.edu.pe",
        "email_alternativo": "jcharca@unap.edu.pe",
        "telefono": "989655958",
        "horario": "8:00 a 13:00 horas",
        "atencion": "Lunes a viernes de 8:00 a 13:00 h",
        "ubicacion": "Pabellón antiguo de E.P. de Trabajo Social, Segundo Piso, Oficina 205, Ciudad Universitaria",
        "alias": "Trabajo Social, FTS, Servicio Social"
      }
    },
    {
      "text": "FACULTAD: FACULTAD_DE_ENFERMERIA\nCOORDINADOR: Edson Gilmar Quispe Ponce\nEMAIL: enfermeria.investigacion@unap.edu.pe\nTELÉFONO: 958748583\nHORARIO: 8:00 a 16:30 horas\nUBICACIÓN: Pabellón Administrativo de la Facultad de Enfermería, Tercer piso, Oficina 311, Ciudad Universitaria\nATENCIÓN: Lunes a viernes de 8:00 a 16:30 h\nALIAS: Enfermería, Escuela de Enfermería\n\nINFORMACIÓN COMPLETA:\nTIPO: coordinador NOMBRE: Edson Gilmar Quispe Ponce EMAIL: enfermeria.investigacion@unap.edu.pe TELEFONO: 958748583 HORARIO: 8:00 a 16:30 horas ATENCION: Lunes a viernes de 8:00 a 16:30 h UBICACION: Pabellón Administrativo de la Facultad de Enfermería, Tercer piso, Oficina 311, Ciudad Universitaria ALIAS: Enfermería, Escuela de Enfermería",
      "source": "coordinadores",
      "type": "coordinador",
      "facultad": "FACULTAD_DE_ENFERMERIA",
      "entidad": "facultad",
      "metadata": {
        "tipo": "coordinador",
        "nombre": "Edson Gilmar Quispe Ponce",
        "email": "enfermeria.investigacion@unap.edu.pe",
        "telefono": "958748583",
        "horario": "8:00 a 16:30 horas",
        "atencion": "Lunes a viernes de 8:00 a 16:30 h",
        "ubicacion": "Pabellón Administrativo de la Facultad de Enfermería, Tercer piso, Oficina 311, Ciudad Universitaria",
        "alias": "Enfermería, Escuela de Enfermería"
      }
    },
    {
      "text": "FACULTAD: FACULTAD_DE_CIENCIAS_SOCIALES\nCOORDINADOR: Elsa Maria Mamani Tapia\nEMAIL: investigacion.fcs@unap.edu.pe\nTELÉFONO: 990129411\nHORARIO: 7:30 a 14:30 horas\nUBICACIÓN: Pabellón antiguo de la E.P. de Sociología, Primer piso, Oficina 103, Ciudad Universitaria\nATENCIÓN: Lunes a viernes de 7:30 a 14:30 h\nALIAS: Ciencias Sociales, FCS, Sociología, Antropología\n\nINFORMACIÓN COMPLETA:\nTIPO: coordinador NOMBRE: Elsa Maria Mamani Tapia EMAIL: investigacion.fcs@unap.edu.pe TELEFONO: 990129411 HORARIO: 7:30 a 14:30 horas ATENCION: Lunes a viernes de 7:30 a 14:30 h UBICACION: Pabellón antiguo de la E.P. de Sociología, Primer piso, Oficina 103, Ciudad Universitaria ALIAS: Ciencias Sociales, FCS, Sociología, Antropología",
      "source": "coordinadores",
      "type": "coordinador",
      "facultad": "FACULTAD_DE_CIENCIAS_SOCIALES",
      "entidad": "facultad",
      "metadata": {
        "tipo": "coordinador",
        "nombre": "Elsa Maria Mamani Tapia",
        "email": "investigacion.fcs@unap.edu.pe",
        "telefono": "990129411",
        "horario": "7:30 a 14:30 horas",
        "atencion": "Lunes a viernes de 7:30 a 14:30 h",
        "ubicacion": "Pabellón antiguo de la E.P. de Sociología, Primer piso, Oficina 103, Ciudad Universitaria",
        "alias": "Ciencias Sociales, FCS, Sociología, Antropología"
      }
    },
    {
      "text": "FACULTAD: FACULTAD_DE_INGENIERIA_DE_MINAS\nCOORDINADOR: Jose Carlos Cucho Cruz\nEMAIL: jcucho@unap.edu.pe\nTELÉFONO: 982379208\nHORARIO: 8:00 a 14:30 horas\nUBICACIÓN: Pabellón Antiguo de la E.P Ing. Minas, Cuarto Piso, Oficina 406, Ciudad Universitaria\nATENCIÓN: Lunes a viernes de 8:00 a 14:30 h\nALIAS: Ingeniería de Minas, Minas, FIM\n\nINFORMACIÓN COMPLETA:\nTIPO: coordinador NOMBRE: Jose Carlos Cucho Cruz EMAIL: jcucho@unap.edu.pe TELEFONO: 982379208 HORARIO: 8:00 a 14:30 horas ATENCION: Lunes a viernes de 8:00 a 14:30 h UBICACION: Pabellón Antiguo de la E.P Ing. Minas, Cuarto Piso, Oficina 406, Ciudad Universitaria ALIAS: Ingeniería de Minas, Minas, FIM",
      "source": "coordinadores",
      "type": "coordinador",
      "facultad": "FACULTAD_DE_INGENIERIA_DE_MINAS",
      "entidad": "facultad",
      "metadata": {
        "tipo": "coordinador",
        "nombre": "Jose Carlos Cucho Cruz",
        "email": "jcucho@unap.edu.pe",
        "telefono": "982379208",
        "horario": "8:00 a 14:30 horas",
        "atencion": "Lunes a viernes de 8:00 a 14:30 h",
        "ubicacion": "Pabellón Antiguo de la E.P Ing. Minas, Cuarto Piso, Oficina 406, Ciudad Universitaria",
        "alias": "Ingeniería de Minas, Minas, FIM"
      }
    },
    {
      "text": "FACULTAD: FACULTAD_DE_CIENCIAS_BIOLOGICAS\nCOORDINADOR: Yrma Ruelas Ortega\nEMAIL: yruelas@unap.edu.pe\nTELÉFONO: 955660218\nHORARIO: 8:00 a 16:30 horas\nUBICACIÓN: Pabellón de Biomédicas parte Administrativa, Cuarto piso, Oficina 403, Ciudad Universitaria\nATENCIÓN: Lunes a viernes de 8:00 a 16:30 h\nALIAS: Ciencias Biológicas, Biología, FCB\n\nINFORMACIÓN COMPLETA:\nTIPO: coordinador NOMBRE: Yrma Ruelas Ortega EMAIL: yruelas@unap.edu.pe TELEFONO: 955660218 HORARIO: 8:00 a 16:30 horas ATENCION: Lunes a viernes de 8:00 a 16:30 h UBICACION: Pabellón de Biomédicas parte Administrativa, Cuarto piso, Oficina 403, Ciudad Universitaria ALIAS: Ciencias Biológicas, Biología, FCB",
      "source": "coordinadores",
      "type": "coordinador",
      "facultad": "FACULTAD_DE_CIENCIAS_BIOLOGICAS",
      "entidad": "facultad",
      "metadata": {
        "tipo": "coordinador",
        "nombre": "Yrma Ruelas Ortega",
        "email": "yruelas@unap.edu.pe",
        "telefono": "955660218",
        "horario": "8:00 a 16:30 horas",
        "atencion": "Lunes a viernes de 8:00 a 16:30 h",
        "ubicacion": "Pabellón de Biomédicas parte Administrativa, Cuarto piso, Oficina 403, Ciudad Universitaria",
        "alias": "Ciencias Biológicas, Biología, FCB"
      }
    },
    {
      "text": "FACULTAD: FACULTAD_DE_CIENCIAS_DE_LA_EDUCACION\nCOORDINADOR: Ruth Mery Cruz Huisa\nEMAIL: rcruzh@unap.edu.pe\nTELÉFONO: 982311128\nHORARIO: Consultar directamente\nUBICACIÓN: Por confirmar\nATENCIÓN: Por confirmar\nALIAS: Ciencias de la Educación, Educación, FCEDUC\n\nINFORMACIÓN COMPLETA:\nTIPO: coordinador NOMBRE: Ruth Mery Cruz Huisa EMAIL: rcruzh@unap.edu.pe TELEFONO: 982311128 HORARIO: Consultar directamente ATENCION: Por confirmar UBICACION: Por confirmar ALIAS: Ciencias de la Educación, Educación, FCEDUC",
      "source": "coordinadores",
      "type": "coordinador",
      "facultad": "FACULTAD_DE_CIENCIAS_DE_LA_EDUCACION",
      "entidad": "facultad",
      "metadata": {
        "tipo": "coordinador",
        "nombre": "Ruth Mery Cruz Huisa",
        "email": "rcruzh@unap.edu.pe",
        "telefono": "982311128",
        "horario": "Consultar directamente",
        "atencion": "Por confirmar",
        "ubicacion": "Por confirmar",
        "alias": "Ciencias de la Educación, Educación, FCEDUC"
      }
    },
    {
      "text": "FACULTAD: FACULTAD_DE_INGENIERIA_ESTADISTICA_E_INFORMATICA\nCOORDINADOR: Coordinación de Estadística\nEMAIL: bcanqui@unap.edu.pe\nTELÉFONO: 951524868\nHORARIO: 8:00 a 14:30 horas\nUBICACIÓN: Pabellón antiguo de la Facultad de Estadística e Informática, Tercer Piso, Ciudad Universitaria\nATENCIÓN: Lunes a viernes de 8:00 a 14:30 h\nALIAS: Estadística e Informática, FIEI, Estadística, Informática, Sistemas\n\nINFORMACIÓN COMPLETA:\nTIPO: coordinador NOMBRE: Coordinación de Estadística EMAIL: bcanqui@unap.edu.pe TELEFONO: 951524868 HORARIO: 8:00 a 14:30 horas ATENCION: Lunes a viernes de 8:00 a 14:30 h UBICACION: Pabellón antiguo de la Facultad de Estadística e Informática, Tercer Piso, Ciudad Universitaria ALIAS: Estadística e Informática, FIEI, Estadística, Informática, Sistemas",
      "source": "coordinadores",
      "type": "coordinador",
      "facultad": "FACULTAD_DE_INGENIERIA_ESTADISTICA_E_INFORMATICA",
      "entidad": "facultad",
      "metadata": {
        "tipo": "coordinador",
        "nombre": "Coordinación de Estadística",
        "email": "bcanqui@unap.edu.pe",
        "telefono": "951524868",
        "horario": "8:00 a 14:30 horas",
        "atencion": "Lunes a viernes de 8:00 a 14:30 h",
        "ubicacion": "Pabellón antiguo de la Facultad de Estadística e Informática, Tercer Piso, Ciudad Universitaria",
        "alias": "Estadística e Informática, FIEI, Estadística, Informática, Sistemas"
      }
    },
    {
      "text": "FACULTAD: FACULTAD_DE_CIENCIAS_JURIDICAS_Y_POLITICAS\nCOORDINADOR: Nadia Yanett Pineda Chaquilla\nEMAIL: npineda@unap.edu.pe\nTELÉFONO: 951591608\nHORARIO: 8:00 a 15:00 horas\nUBICACIÓN: Edificio de la Facultad de Ciencias Jurídicas y políticas, Jr. Grau esquina con Jr. Conde de Lemus, Cuarto piso, Oficina 503\nATENCIÓN: Lunes a viernes de 8:00 a 15:00 h\nALIAS: Ciencias Jurídicas, Derecho, FCJP\n\nINFORMACIÓN COMPLETA:\nTIPO: coordinador NOMBRE: Nadia Yanett Pineda Chaquilla EMAIL: npineda@unap.edu.pe TELEFONO: 951591608 HORARIO: 8:00 a 15:00 horas ATENCION: Lunes a viernes de 8:00 a 15:00 h UBICACION: Edificio de la Facultad de Ciencias Jurídicas y políticas, Jr. Grau esquina con Jr. Conde de Lemus, Cuarto piso, Oficina 503 ALIAS: Ciencias Jurídicas, Derecho, FCJP",
      "source": "coordinadores",
      "type": "coordinador",
      "facultad": "FACULTAD_DE_CIENCIAS_JURIDICAS_Y_POLITICAS",
      "entidad": "facultad",
      "metadata": {
        "tipo": "coordinador",
        "nombre": "Nadia Yanett Pineda Chaquilla",
        "email": "npineda@unap.edu.pe",
        "telefono": "951591608",
        "horario": "8:00 a 15:00 horas",
        "atencion": "Lunes a viernes de 8:00 a 15:00 h",
        "ubicacion": "Edificio de la Facultad de Ciencias Jurídicas y políticas, Jr. Grau esquina con Jr. Conde de Lemus, Cuarto piso, Oficina 503",
        "alias": "Ciencias Jurídicas, Derecho, FCJP"
      }
    },
    {
      "text": "FACULTAD: FACULTAD_DE_INGENIERIA_QUIMICA\nCOORDINADOR: Jessica Milena Euribe Puma\nEMAIL: jeuribe@unap.edu.pe\nTELÉFONO: 956668846\nHORARIO: 7:40 a 14:30 horas\nUBICACIÓN: Pabellón de Facultad de Ingeniería Química, Ciudad Universitaria\nATENCIÓN: Lunes a viernes de 7:40 a 14:30 h\nALIAS: Ingeniería Química, FIQ, Química\n\nINFORMACIÓN COMPLETA:\nTIPO: coordinador NOMBRE: Jessica Milena Euribe Puma EMAIL: jeuribe@unap.edu.pe TELEFONO: 956668846 HORARIO: 7:40 a 14:30 horas ATENCION: Lunes a viernes de 7:40 a 14:30 h UBICACION: Pabellón de Facultad de Ingeniería Química, Ciudad Universitaria ALIAS: Ingeniería Química, FIQ, Química",
      "source": "coordinadores",
      "type": "coordinador",
      "facultad": "FACULTAD_DE_INGENIERIA_QUIMICA",
      "entidad": "facultad",
      "metadata": {
        "tipo": "coordinador",
        "nombre": "Jessica Milena Euribe Puma",
        "email": "jeuribe@unap.edu.pe",
        "telefono": "956668846",
        "horario": "7:40 a 14:30 horas",
        "atencion": "Lunes a viernes de 7:40 a 14:30 h",
        "ubicacion": "Pabellón de Facultad de Ingeniería Química, Ciudad Universitaria",
        "alias": "Ingeniería Química, FIQ, Química"
      }
    },
    {
      "text": "FACULTAD: FACULTAD_DE_CIENCIAS_DE_LA_SALUD\nCOORDINADOR: Eufemia Marron Huaranca\nEMAIL: emarron@unap.edu.pe\nTELÉFONO: 951676890\nHORARIO: 7:30 a 14:30 horas\nUBICACIÓN: Pabellón Antiguo de la E.P. de Nutrición y Odontología, Segundo piso, Oficina 202, Ciudad Universitaria\nATENCIÓN: Lunas a viernes de 7:30 a 14:30 h\nALIAS: Ciencias de la Salud, Salud, Nutrición, Odontología\n\nINFORMACIÓN COMPLETA:\nTIPO: coordinador NOMBRE: Eufemia Marron Huaranca EMAIL: emarron@unap.edu.pe TELEFONO: 951676890 HORARIO: 7:30 a 14:30 horas ATENCION: Lunas a viernes de 7:30 a 14:30 h UBICACION: Pabellón Antiguo de la E.P. de Nutrición y Odontología, Segundo piso, Oficina 202, Ciudad Universitaria ALIAS: Ciencias de la Salud, Salud, Nutrición, Odontología",
      "source": "coordinadores",
      "type": "coordinador",
      "facultad": "FACULTAD_DE_CIENCIAS_DE_LA_SALUD",
      "entidad": "facultad",
      "metadata": {
        "tipo": "coordinador",
        "nombre": "Eufemia Marron Huaranca",
        "email": "emarron@unap.edu.pe",
        "telefono": "951676890",
        "horario": "7:30 a 14:30 horas",
        "atencion": "Lunas a viernes de 7:30 a 14:30 h",
        "ubicacion": "Pabellón Antiguo de la E.P. de Nutrición y Odontología, Segundo piso, Oficina 202, Ciudad Universitaria",
        "alias": "Ciencias de la Salud, Salud, Nutrición, Odontología"
      }
    },
    {
      "text": "FACULTAD: FACULTAD_DE_INGENIERIA_GEOLOGICA_Y_METALURGICA\nCOORDINADOR: Yenny Aguirre Luna\nEMAIL: yaguirre@unap.edu.pe\nTELÉFONO: 919666026\nHORARIO: 8:30 a 14:30 horas\nUBICACIÓN: Pabellón de Facultad de Ingeniería Geológica y Metalúrgica, Tercer piso, Ciudad Universitaria\nATENCIÓN: Lunes a viernes de 8:30 a 14:30 h\nALIAS: Geológica y Metalúrgica, Geología, Metalurgia, FIGMM\n\nINFORMACIÓN COMPLETA:\nTIPO: coordinador NOMBRE: Yenny Aguirre Luna EMAIL: yaguirre@unap.edu.pe TELEFONO: 919666026 HORARIO: 8:30 a 14:30 horas ATENCION: Lunes a viernes de 8:30 a 14:30 h UBICACION: Pabellón de Facultad de Ingeniería Geológica y Metalúrgica, Tercer piso, Ciudad Universitaria ALIAS: Geológica y Metalúrgica, Geología, Metalurgia, FIGMM",
      "source": "coordinadores",
      "type": "coordinador",
      "facultad": "FACULTAD_DE_INGENIERIA_GEOLOGICA_Y_METALURGICA",
      "entidad": "facultad",
      "metadata": {
        "tipo": "coordinador",
        "nombre": "Yenny Aguirre Luna",
        "email": "yaguirre@unap.edu.pe",
        "telefono": "919666026",
        "horario": "8:30 a 14:30 horas",
        "atencion": "Lunes a viernes de 8:30 a 14:30 h",
        "ubicacion": "Pabellón de Facultad de Ingeniería Geológica y Metalúrgica, Tercer piso, Ciudad Universitaria",
        "alias": "Geológica y Metalúrgica, Geología, Metalurgia, FIGMM"
      }
    },
    {
      "text": "FACULTAD: FACULTAD_DE_INGENIERIA_CIVIL_Y_ARQUITECTURA\nCOORDINADOR: Hilda Fidela Yanarico Monroy\nEMAIL: hyanarico@unap.edu.pe\nTELÉFONO: 951510290\nHORARIO: 8:00 a 14:30 horas\nUBICACIÓN: Pabellón de la E.P. de Ciencias Físico Matemáticas, Segundo piso, Oficina 210, Ciudad Universitaria\nATENCIÓN: Lunes a viernes de 8:00 a 14:30 h\nALIAS: Ingeniería Civil, Arquitectura, FICA, Civil\n\nINFORMACIÓN COMPLETA:\nTIPO: coordinador NOMBRE: Hilda Fidela Yanarico Monroy EMAIL: hyanarico@unap.edu.pe TELEFONO: 951510290 HORARIO: 8:00 a 14:30 horas ATENCION: Lunes a viernes de 8:00 a 14:30 h UBICACION: Pabellón de la E.P. de Ciencias Físico Matemáticas, Segundo piso, Oficina 210, Ciudad Universitaria ALIAS: Ingeniería Civil, Arquitectura, FICA, Civil",
      "source": "coordinadores",
      "type": "coordinador",
      "facultad": "FACULTAD_DE_INGENIERIA_CIVIL_Y_ARQUITECTURA",
      "entidad": "facultad",
      "metadata": {
        "tipo": "coordinador",
        "nombre": "Hilda Fidela Yanarico Monroy",
        "email": "hyanarico@unap.edu.pe",
        "telefono": "951510290",
        "horario": "8:00 a 14:30 horas",
        "atencion": "Lunes a viernes de 8:00 a 14:30 h",
        "ubicacion": "Pabellón de la E.P. de Ciencias Físico Matemáticas, Segundo piso, Oficina 210, Ciudad Universitaria",
        "alias": "Ingeniería Civil, Arquitectura, FICA, Civil"
      }
    },
    {
      "text": "FACULTAD: FACULTAD_DE_INGENIERIA_AGRICOLA\nCOORDINADOR: Angel Jogues Calsina Ponce\nEMAIL: agricola.investigacion@unap.edu.pe\nTELÉFONO: 946549806\nHORARIO: 7:55 a 15:30 horas\nUBICACIÓN: Pabellón de la E.P. de Ingeniería Agrícola, Tercer piso, Oficina 310, Ciudad Universitaria\nATENCIÓN: Lunes a viernes de 7:55 a 15:30 h\nALIAS: Ingeniería Agrícola, Agrícola, FIA\n\nINFORMACIÓN COMPLETA:\nTIPO: coordinador NOMBRE: Angel Jogues Calsina Ponce EMAIL: agricola.investigacion@unap.edu.pe TELEFONO: 946549806 HORARIO: 7:55 a 15:30 horas ATENCION: Lunes a viernes de 7:55 a 15:30 h UBICACION: Pabellón de la E.P. de Ingeniería Agrícola, Tercer piso, Oficina 310, Ciudad Universitaria ALIAS: Ingeniería Agrícola, Agrícola, FIA",
      "source": "coordinadores",
      "type": "coordinador",
      "facultad": "FACULTAD_DE_INGENIERIA_AGRICOLA",
      "entidad": "facultad",
      "metadata": {
        "tipo": "coordinador",
        "nombre": "Angel Jogues Calsina Ponce",
        "email": "agricola.investigacion@unap.edu.pe",
        "telefono": "946549806",
        "horario": "7:55 a 15:30 horas",
        "atencion": "Lunes a viernes de 7:55 a 15:30 h",
        "ubicacion": "Pabellón de la E.P. de Ingeniería Agrícola, Tercer piso, Oficina 310, Ciudad Universitaria",
        "alias": "Ingeniería Agrícola, Agrícola, FIA"
      }
    },
    {
      "text": "FACULTAD: FACULTAD_DE_MEDICINA_HUMANA\nCOORDINADOR: Nilda Elizabeth Nuñez Pari\nEMAIL: uinvestigacion.fmh@unap.edu.pe\nTELÉFONO: 982306639\nHORARIO: 8:00 a 14:30 horas\nUBICACIÓN: Pabellón biomédicas administrativo, Segundo piso, Oficina 213, Ciudad Universitaria\nATENCIÓN: Lunes a viernes de 8:00 a 14:30 h\nALIAS: Medicina Humana, Medicina, FMH\n\nINFORMACIÓN COMPLETA:\nTIPO: coordinador NOMBRE: Nilda Elizabeth Nuñez Pari EMAIL: uinvestigacion.fmh@unap.edu.pe TELEFONO: 982306639 HORARIO: 8:00 a 14:30 horas ATENCION: Lunes a viernes de 8:00 a 14:30 h UBICACION: Pabellón biomédicas administrativo, Segundo piso, Oficina 213, Ciudad Universitaria ALIAS: Medicina Humana, Medicina, FMH",
      "source": "coordinadores",
      "type": "coordinador",
      "facultad": "FACULTAD_DE_MEDICINA_HUMANA",
      "entidad": "facultad",
      "metadata": {
        "tipo": "coordinador",
        "nombre": "Nilda Elizabeth Nuñez Pari",
        "email": "uinvestigacion.fmh@unap.edu.pe",
        "telefono": "982306639",
        "horario": "8:00 a 14:30 horas",
        "atencion": "Lunes a viernes de 8:00 a 14:30 h",
        "ubicacion": "Pabellón biomédicas administrativo, Segundo piso, Oficina 213, Ciudad Universitaria",
        "alias": "Medicina Humana, Medicina, FMH"
      }
    },
    {
      "text": "FACULTAD: FACULTAD_DE_INGENIERIA_MECANICA_ELECTRICA_ELECTRONICA_Y_SISTEMAS\nCOORDINADOR: Maritza Yolanda Quea Gutierrez\nEMAIL: mquea@unap.edu.pe\nTELÉFONO: 968823210\nHORARIO: 8:00 a 14:30 horas\nUBICACIÓN: Pabellón de la Escuela Profesional de Ingeniería Mecánica Eléctrica, Tercer piso, Ciudad Universitaria\nATENCIÓN: Lunes a viernes de 8:00 a 14:30 h\nALIAS: Ingeniería Mecánica Eléctrica, FIMEES, Mecánica, Eléctrica, Electrónica, Sistemas\n\nINFORMACIÓN COMPLETA:\nTIPO: coordinador NOMBRE: Maritza Yolanda Quea Gutierrez EMAIL: mquea@unap.edu.pe TELEFONO: 968823210 HORARIO: 8:00 a 14:30 horas ATENCION: Lunes a viernes de 8:00 a 14:30 h UBICACION: Pabellón de la Escuela Profesional de Ingeniería Mecánica Eléctrica, Tercer piso, Ciudad Universitaria ALIAS: Ingeniería Mecánica Eléctrica, FIMEES, Mecánica, Eléctrica, Electrónica, Sistemas",
      "source": "coordinadores",
      "type": "coordinador",
      "facultad": "FACULTAD_DE_INGENIERIA_MECANICA_ELECTRICA_ELECTRONICA_Y_SISTEMAS",
      "entidad": "facultad",
      "metadata": {
        "tipo": "coordinador",
        "nombre": "Maritza Yolanda Quea Gutierrez",
        "email": "mquea@unap.edu.pe",
        "telefono": "968823210",
        "horario": "8:00 a 14:30 horas",
        "atencion": "Lunes a viernes de 8:00 a 14:30 h",
        "ubicacion": "Pabellón de la Escuela Profesional de Ingeniería Mecánica Eléctrica, Tercer piso, Ciudad Universitaria",
        "alias": "Ingeniería Mecánica Eléctrica, FIMEES, Mecánica, Eléctrica, Electrónica, Sistemas"
      }
    },
    {
      "text": "FACULTAD: FACULTAD_DE_CIENCIAS_ADMINISTRATIVAS_Y_HUMANAS\nCOORDINADOR: Marisol Huaman Flores\nEMAIL: fcah.ui@unap.edu.pe\nTELÉFONO: 918432768\nHORARIO: 8:30 a 14:30 horas\nUBICACIÓN: Pabellón antiguo de la E.P. de Administración, Primer piso, Oficina 102, Ciudad Universitaria\nATENCIÓN: Lunes a viernes de 8:30 a 14:30 h\nALIAS: Ciencias Administrativas, Administrativas, Humanas, FCAH\n\nINFORMACIÓN COMPLETA:\nTIPO: coordinador NOMBRE: Marisol Huaman Flores EMAIL: fcah.ui@unap.edu.pe TELEFONO: 918432768 HORARIO: 8:30 a 14:30 horas ATENCION: Lunes a viernes de 8:30 a 14:30 h UBICACION: Pabellón antiguo de la E.P. de Administración, Primer piso, Oficina 102, Ciudad Universitaria ALIAS: Ciencias Administrativas, Administrativas, Humanas, FCAH",
      "source": "coordinadores",
      "type": "coordinador",
      "facultad": "FACULTAD_DE_CIENCIAS_ADMINISTRATIVAS_Y_HUMANAS",
      "entidad": "facultad",
      "metadata": {
        "tipo": "coordinador",
        "nombre": "Marisol Huaman Flores",
        "email": "fcah.ui@unap.edu.pe",
        "telefono": "918432768",
        "horario": "8:30 a 14:30 horas",
        "atencion": "Lunes a viernes de 8:30 a 14:30 h",
        "ubicacion": "Pabellón antiguo de la E.P. de Administración, Primer piso, Oficina 102, Ciudad Universitaria",
        "alias": "Ciencias Administrativas, Administrativas, Humanas, FCAH"
      }
    },
    {
      "text": "ETAPA_PROCESO: ETAPA_PROYECTO_TESIS\nDESCRIPCIÓN: Primera etapa del proceso donde se presenta y aprueba el proyecto de investigación",
      "source": "mapa y procesos",
      "type": "etapa_proceso",
      "titulo": "ETAPA_PROYECTO_TESIS",
      "entidad": "general"
    },
    {
      "text": "ETAPA_PROCESO: ETAPA_BORRADOR_TESIS\nDESCRIPCIÓN: Segunda etapa donde se entrega el borrador completo de la tesis para revisión formal",
      "source": "mapa y procesos",
      "type": "etapa_proceso",
      "titulo": "ETAPA_BORRADOR_TESIS",
      "entidad": "general"
    },
    {
      "text": "ETAPA_PROCESO: ETAPA_SUSTENTACION\nDESCRIPCIÓN: Tercera etapa donde se presenta y defiende la tesis ante el jurado evaluador",
      "source": "mapa y procesos",
      "type": "etapa_proceso",
      "titulo": "ETAPA_SUSTENTACION",
      "entidad": "general"
    },
    {
      "text": "ACTOR_PROCESO: ACTORES_DEL_PROCESO\nDESCRIPCIÓN: Estudiante de 7mo a 10mo semestre, egresado de la UNA Puno",
      "source": "mapa y procesos",
      "type": "actor_proceso",
      "titulo": "ACTORES_DEL_PROCESO",
      "entidad": "general"
    },
    {
      "text": "ACTOR_PROCESO: ACTORES_DEL_PROCESO\nDESCRIPCIÓN: También conocido como Asesor de Tesis, es un docente ordinario de la misma escuela profesional",
      "source": "mapa y procesos",
      "type": "actor_proceso",
      "titulo": "ACTORES_DEL_PROCESO",
      "entidad": "general"
    },
    {
      "text": "ACTOR_PROCESO: ACTORES_DEL_PROCESO\nDESCRIPCIÓN: Docentes ordinarios y contratados de la UNA Puno",
      "source": "mapa y procesos",
      "type": "actor_proceso",
      "titulo": "ACTORES_DEL_PROCESO",
      "entidad": "general"
    },
    {
      "text": "ACTOR_PROCESO: ACTORES_DEL_PROCESO\nDESCRIPCIÓN: Docente ordinario de la escuela profesional",
      "source": "mapa y procesos",
      "type": "actor_proceso",
      "titulo": "ACTORES_DEL_PROCESO",
      "entidad": "general"
    },
    {
      "text": "ACTOR_PROCESO: ACTORES_DEL_PROCESO\nDESCRIPCIÓN: Resuelve conflictos a nivel facultad",
      "source": "mapa y procesos",
      "type": "actor_proceso",
      "titulo": "ACTORES_DEL_PROCESO",
      "entidad": "general"
    },
    {
      "text": "ACTOR_PROCESO: ACTORES_DEL_PROCESO\nDESCRIPCIÓN: Instancia superior para mediación",
      "source": "mapa y procesos",
      "type": "actor_proceso",
      "titulo": "ACTORES_DEL_PROCESO",
      "entidad": "general"
    },
    {
      "text": "ACTOR_PROCESO: ACTORES_DEL_PROCESO\nDESCRIPCIÓN: Administra y desarrolla la plataforma",
      "source": "mapa y procesos",
      "type": "actor_proceso",
      "titulo": "ACTORES_DEL_PROCESO",
      "entidad": "general"
    },
    {
      "text": "ACTOR_PROCESO: ACTORES_DEL_PROCESO\nDESCRIPCIÓN: Guía y supervisa todo el proceso",
      "source": "mapa y procesos",
      "type": "actor_proceso",
      "titulo": "ACTORES_DEL_PROCESO",
      "entidad": "general"
    },
    {
      "text": "PREGUNTA: Si tengo dos carreras, ¿Necesito dos cuentas de correo?\nRESPUESTA: No. Solo necesitas 1 cuenta de correo para administrar todos los servicios de la Plataforma de Gestión de Investigación.",
      "source": "PREGUNTAS f",
      "type": "pregunta_frecuente",
      "pregunta": "Si tengo dos carreras, ¿Necesito dos cuentas de correo?",
      "respuesta": "No. Solo necesitas 1 cuenta de correo para administrar todos los servicios de la Plataforma de Gestión de Investigación.",
      "entidad": "general"
    },
    {
      "text": "PREGUNTA: Yo tenía una cuenta en la plataforma anterior, ¿es necesario actualizar mi contraseña para ingresar a la nueva plataforma?\nRESPUESTA: SÍ. Es necesario que usted actualice su contraseña para acceder a todos los servicios de la Plataforma de Gestión de Investigación.",
      "source": "PREGUNTAS f",
      "type": "pregunta_frecuente",
      "pregunta": "Yo tenía una cuenta en la plataforma anterior, ¿es necesario actualizar mi contraseña para ingresar a la nueva plataforma?",
      "respuesta": "SÍ. Es necesario que usted actualice su contraseña para acceder a todos los servicios de la Plataforma de Gestión de Investigación.",
      "entidad": "general"
    },
    {
      "text": "PREGUNTA: Quiero subir mi tesis / Cómo subir mi tesis\nRESPUESTA: El proceso se realiza a través de la Plataforma de Gestión de la Investigación (PGI) en pgi.vriunap.pe. Debes: 1️⃣ Registrarte con tu correo y contraseña. 2️⃣ Confirmar tu cuenta vía correo electrónico. 3️⃣ Subir tu proyecto de tesis en PDF, junto con el reporte de similitud (Turnitin) firmado por tu director y la declaración jurada sobre autoría y uso ético de IA (Anexo 1).",
      "source": "PREGUNTAS f",
      "type": "pregunta_frecuente",
      "pregunta": "Quiero subir mi tesis / Cómo subir mi tesis",
      "respuesta": "El proceso se realiza a través de la Plataforma de Gestión de la Investigación (PGI) en pgi.vriunap.pe. Debes: 1️⃣ Registrarte con tu correo y contraseña. 2️⃣ Confirmar tu cuenta vía correo electrónico. 3️⃣ Subir tu proyecto de tesis en PDF, junto con el reporte de similitud (Turnitin) firmado por tu director y la declaración jurada sobre autoría y uso ético de IA (Anexo 1).",
      "entidad": "general"
    },
    {
      "text": "PREGUNTA: Puedo realizar mi trámite sin ir a las oficinas?\nRESPUESTA: SÍ. Todo el proceso se realiza de forma digital a través de la Plataforma PGI, desde la carga del proyecto hasta la sustentación y emisión de constancias.",
      "source": "PREGUNTAS f",
      "type": "pregunta_frecuente",
      "pregunta": "Puedo realizar mi trámite sin ir a las oficinas?",
      "respuesta": "SÍ. Todo el proceso se realiza de forma digital a través de la Plataforma PGI, desde la carga del proyecto hasta la sustentación y emisión de constancias.",
      "entidad": "general"
    },
    {
      "text": "PREGUNTA: Cuál es el proceso de desarrollo de una tesis de pregrado?\nRESPUESTA: El proceso completo incluye: 1. Carga del proyecto de tesis. 2. Revisión de formato. 3. Revisión por el director. 4. Revisión por subdirector de investigación. 5. Sorteo de jurados. 6. Revisión por jurados. 7. Dictamen del proyecto. 8. Ejecución (3 meses a 2 años). 9. Carga y revisión del borrador. 10. Dictamen del borrador. 11. Sustentación. 12. Carga del archivo final.",
      "source": "PREGUNTAS f",
      "type": "pregunta_frecuente",
      "pregunta": "Cuál es el proceso de desarrollo de una tesis de pregrado?",
      "respuesta": "El proceso completo incluye: 1. Carga del proyecto de tesis. 2. Revisión de formato. 3. Revisión por el director. 4. Revisión por subdirector de investigación. 5. Sorteo de jurados. 6. Revisión por jurados. 7. Dictamen del proyecto. 8. Ejecución (3 meses a 2 años). 9. Carga y revisión del borrador. 10. Dictamen del borrador. 11. Sustentación. 12. Carga del archivo final.",
      "entidad": "general"
    },
    {
      "text": "PREGUNTA: ¿Dónde puedo obtener los reglamentos vigentes del Vicerrectorado de Investigación?\nRESPUESTA: Para acceder al reglamento accede al sitio web: web.vriunap.pe y revisa la sección reglamentos.",
      "source": "PREGUNTAS f",
      "type": "pregunta_frecuente",
      "pregunta": "¿Dónde puedo obtener los reglamentos vigentes del Vicerrectorado de Investigación?",
      "respuesta": "Para acceder al reglamento accede al sitio web: web.vriunap.pe y revisa la sección reglamentos.",
      "entidad": "general"
    },
    {
      "text": "PREGUNTA: Quiero información sobre el coordinador\nRESPUESTA: En el reglamento se aclara que el coordinador de investigación es el personal administrativo de investigación de la unidad de investigación de cada facultad. Son responsables de revisar el formato inicial del proyecto y del borrador de tesis.",
      "source": "PREGUNTAS f",
      "type": "pregunta_frecuente",
      "pregunta": "Quiero información sobre el coordinador",
      "respuesta": "En el reglamento se aclara que el coordinador de investigación es el personal administrativo de investigación de la unidad de investigación de cada facultad. Son responsables de revisar el formato inicial del proyecto y del borrador de tesis.",
      "entidad": "general"
    },
    {
      "text": "PREGUNTA: ¿Es posible conocer quiénes son los miembros del jurado?\nRESPUESTA: SÍ. Los miembros del jurado son de conocimiento público desde que el Sub Director de la Unidad de Investigación realiza el sorteo.",
      "source": "PREGUNTAS f",
      "type": "pregunta_frecuente",
      "pregunta": "¿Es posible conocer quiénes son los miembros del jurado?",
      "respuesta": "SÍ. Los miembros del jurado son de conocimiento público desde que el Sub Director de la Unidad de Investigación realiza el sorteo.",
      "entidad": "general"
    },
    {
      "text": "PREGUNTA: En la etapa de proyecto, ¿es necesario que los 3 jurados realicen las correcciones para subir el archivo corregido?\nRESPUESTA: SÍ, si es posible siempre y cuando 2 jurados hayan finalizado el proceso de corrección y el otro jurado haya excedido el tiempo de corrección establecido.",
      "source": "PREGUNTAS f",
      "type": "pregunta_frecuente",
      "pregunta": "En la etapa de proyecto, ¿es necesario que los 3 jurados realicen las correcciones para subir el archivo corregido?",
      "respuesta": "SÍ, si es posible siempre y cuando 2 jurados hayan finalizado el proceso de corrección y el otro jurado haya excedido el tiempo de corrección establecido.",
      "entidad": "general"
    },
    {
      "text": "PREGUNTA: ¿Es necesario contar con el bachiller para iniciar con la etapa de borrador de tesis?\nRESPUESTA: SÍ. Es un requisito indispensable contar con el grado de Bachiller para iniciar con la etapa de borrador de tesis.",
      "source": "PREGUNTAS f",
      "type": "pregunta_frecuente",
      "pregunta": "¿Es necesario contar con el bachiller para iniciar con la etapa de borrador de tesis?",
      "respuesta": "SÍ. Es un requisito indispensable contar con el grado de Bachiller para iniciar con la etapa de borrador de tesis.",
      "entidad": "general"
    },
    {
      "text": "PREGUNTA: ¿Puedo iniciar la etapa del borrador de tesis antes de los 90 días de ejecución del proyecto?\nRESPUESTA: NO. El tiempo mínimo de ejecución del proyecto de tesis es de 90 días.",
      "source": "PREGUNTAS f",
      "type": "pregunta_frecuente",
      "pregunta": "¿Puedo iniciar la etapa del borrador de tesis antes de los 90 días de ejecución del proyecto?",
      "respuesta": "NO. El tiempo mínimo de ejecución del proyecto de tesis es de 90 días.",
      "entidad": "general"
    },
    {
      "text": "PREGUNTA: Cómo inicio mi proyecto de tesis?\nRESPUESTA: Debes: 1️⃣ Registrar y confirmar tu cuenta en la PGI. 2️⃣ Contar con un director de tesis (docente ordinario de tu escuela y sub-línea de investigación). 3️⃣ Subir el proyecto con el formato establecido, el reporte de similitud ≤20% y la declaración jurada de autoría.",
      "source": "PREGUNTAS f",
      "type": "pregunta_frecuente",
      "pregunta": "Cómo inicio mi proyecto de tesis?",
      "respuesta": "Debes: 1️⃣ Registrar y confirmar tu cuenta en la PGI. 2️⃣ Contar con un director de tesis (docente ordinario de tu escuela y sub-línea de investigación). 3️⃣ Subir el proyecto con el formato establecido, el reporte de similitud ≤20% y la declaración jurada de autoría.",
      "entidad": "general"
    },
    {
      "text": "PREGUNTA: Quiero saber el sorteo de mis jurados\nRESPUESTA: El sorteo de jurados se realiza automáticamente en la PGI. Se eligen 3 docentes de la UNA Puno. Al menos uno debe ser docente ordinario de tu escuela. El presidente se asigna por grado, categoría y antigüedad. Puedes ver los resultados en tu panel.",
      "source": "PREGUNTAS f",
      "type": "pregunta_frecuente",
      "pregunta": "Quiero saber el sorteo de mis jurados",
      "respuesta": "El sorteo de jurados se realiza automáticamente en la PGI. Se eligen 3 docentes de la UNA Puno. Al menos uno debe ser docente ordinario de tu escuela. El presidente se asigna por grado, categoría y antigüedad. Puedes ver los resultados en tu panel.",
      "entidad": "general"
    },
    {
      "text": "PREGUNTA: Quiénes pueden ser mis jurados?\nRESPUESTA: Tres docentes de la UNA-Puno, que pertenezcan a la sublinea de investigacion de tu trabajo de tu escuela porfesional que seran sorteados aleatoriamente por el Sub Director de la Unidad de Investigacion de tu Facultad a travez de la Plataforma de Gestión de la Investigación (PGI). Al menos uno debe ser docente ordinario de tu escuela.",
      "source": "PREGUNTAS f",
      "type": "pregunta_frecuente",
      "pregunta": "Quiénes pueden ser mis jurados?",
      "respuesta": "Tres docentes de la UNA-Puno, que pertenezcan a la sublinea de investigacion de tu trabajo de tu escuela porfesional que seran sorteados aleatoriamente por el Sub Director de la Unidad de Investigacion de tu Facultad a travez de la Plataforma de Gestión de la Investigación (PGI). Al menos uno debe ser docente ordinario de tu escuela.",
      "entidad": "general"
    },
    {
      "text": "PREGUNTA: ¿Es necesario que el director de la tesis o el asesor de la tesis firme mi proyecto para poder cargar mi proyecto a la Plataforma de Gestión de la Investigación?\nRESPUESTA: SÍ. Es necesario que tu director o asesor revise previamente tu proyecto y firme el proyecto además del reporte de similitud para que puedas cargarlo a la plataforma e iniciar el proceso.",
      "source": "PREGUNTAS f",
      "type": "pregunta_frecuente",
      "pregunta": "¿Es necesario que el director de la tesis o el asesor de la tesis firme mi proyecto para poder cargar mi proyecto a la Plataforma de Gestión de la Investigación?",
      "respuesta": "SÍ. Es necesario que tu director o asesor revise previamente tu proyecto y firme el proyecto además del reporte de similitud para que puedas cargarlo a la plataforma e iniciar el proceso.",
      "entidad": "general"
    },
    {
      "text": "PREGUNTA: ¿Es posible agregar a mi proyecto un co-asesor externo?\nRESPUESTA: SÍ. El reglamento actual lo permite, siempre que cumpla con los requisitos establecidos.",
      "source": "PREGUNTAS f",
      "type": "pregunta_frecuente",
      "pregunta": "¿Es posible agregar a mi proyecto un co-asesor externo?",
      "respuesta": "SÍ. El reglamento actual lo permite, siempre que cumpla con los requisitos establecidos.",
      "entidad": "general"
    },
    {
      "text": "PREGUNTA: ¿Cómo me registro para ser un co-asesor externo?\nRESPUESTA: Debes tener una cuenta en la PGI y activar el perfil de investigador. Luego podrás postular como co-asesor y la Dirección del Instituto de Investigación evaluará tu solicitud.",
      "source": "PREGUNTAS f",
      "type": "pregunta_frecuente",
      "pregunta": "¿Cómo me registro para ser un co-asesor externo?",
      "respuesta": "Debes tener una cuenta en la PGI y activar el perfil de investigador. Luego podrás postular como co-asesor y la Dirección del Instituto de Investigación evaluará tu solicitud.",
      "entidad": "general"
    },
    {
      "text": "PREGUNTA: ¿Cuáles son las causales técnicas del rechazo de mi proyecto, luego de haberlo subido a la Plataforma?\nRESPUESTA: Si el proyecto no cumple con el formato establecido en el reglamento (disponible para descarga en la plataforma), será devuelto al tesista.",
      "source": "PREGUNTAS f",
      "type": "pregunta_frecuente",
      "pregunta": "¿Cuáles son las causales técnicas del rechazo de mi proyecto, luego de haberlo subido a la Plataforma?",
      "respuesta": "Si el proyecto no cumple con el formato establecido en el reglamento (disponible para descarga en la plataforma), será devuelto al tesista.",
      "entidad": "general"
    },
    {
      "text": "PREGUNTA: ¿Qué incluye el formato que debo respetar en el proyecto de tesis?\nRESPUESTA: Debe cumplir con la numeración continua, la estructura de secciones, el formato general, indentación y espaciado.",
      "source": "PREGUNTAS f",
      "type": "pregunta_frecuente",
      "pregunta": "¿Qué incluye el formato que debo respetar en el proyecto de tesis?",
      "respuesta": "Debe cumplir con la numeración continua, la estructura de secciones, el formato general, indentación y espaciado.",
      "entidad": "general"
    },
    {
      "text": "PREGUNTA: ¿El archivo de borrador de tesis también debe contener la numeración continua?\nRESPUESTA: SÍ. Es necesario que también contenga numeración continua.",
      "source": "PREGUNTAS f",
      "type": "pregunta_frecuente",
      "pregunta": "¿El archivo de borrador de tesis también debe contener la numeración continua?",
      "respuesta": "SÍ. Es necesario que también contenga numeración continua.",
      "entidad": "general"
    },
    {
      "text": "PREGUNTA: ¿Dónde encuentro los formatos de proyecto de tesis, borrador de tesis, informe de correcciones, declaración jurada sobre autoría, autenticidad y uso ético de IA?\nRESPUESTA: Puedes descargarlos desde el panel del tesista → formatos y plantillas, o solicitarlos al personal administrativo de tu unidad de investigación.",
      "source": "PREGUNTAS f",
      "type": "pregunta_frecuente",
      "pregunta": "¿Dónde encuentro los formatos de proyecto de tesis, borrador de tesis, informe de correcciones, declaración jurada sobre autoría, autenticidad y uso ético de IA?",
      "respuesta": "Puedes descargarlos desde el panel del tesista → formatos y plantillas, o solicitarlos al personal administrativo de tu unidad de investigación.",
      "entidad": "general"
    },
    {
      "text": "PREGUNTA: ¿Qué es el informe de correcciones en el proyecto de tesis?\nRESPUESTA: Es el documento que acompaña al proyecto corregido, y que deberas cargar a la plataforma junto con tu archivo de proyecto. Contiene el número de línea, observación del jurado y la descripción de la corrección, firmado por el director.",
      "source": "PREGUNTAS f",
      "type": "pregunta_frecuente",
      "pregunta": "¿Qué es el informe de correcciones en el proyecto de tesis?",
      "respuesta": "Es el documento que acompaña al proyecto corregido, y que deberas cargar a la plataforma junto con tu archivo de proyecto. Contiene el número de línea, observación del jurado y la descripción de la corrección, firmado por el director.",
      "entidad": "general"
    },
    {
      "text": "PREGUNTA: En qué puedes ayudarme?\nRESPUESTA: Puedo ayudarte a entender todas las etapas del proceso de tesis, desde la carga del proyecto hasta la sustentación, según el reglamento de la UNA Puno. También puedo explicar plazos, requisitos, roles de jurados y uso de la PGI. y brindarte las sublineas de investigación de tu escuela profesional.",
      "source": "PREGUNTAS f",
      "type": "pregunta_frecuente",
      "pregunta": "En qué puedes ayudarme?",
      "respuesta": "Puedo ayudarte a entender todas las etapas del proceso de tesis, desde la carga del proyecto hasta la sustentación, según el reglamento de la UNA Puno. También puedo explicar plazos, requisitos, roles de jurados y uso de la PGI. y brindarte las sublineas de investigación de tu escuela profesional.",
      "entidad": "general"
    },
    {
      "text": "PREGUNTA: Por qué me das dos respuestas?\nRESPUESTA: El chatbot puede ofrecer respuestas complementarias o alternativas. Si ves respuestas duplicadas o inconsistentes, se debe a la configuración del sistema.",
      "source": "PREGUNTAS f",
      "type": "pregunta_frecuente",
      "pregunta": "Por qué me das dos respuestas?",
      "respuesta": "El chatbot puede ofrecer respuestas complementarias o alternativas. Si ves respuestas duplicadas o inconsistentes, se debe a la configuración del sistema.",
      "entidad": "general"
    },
    {
      "text": "ARTÍCULO: INTRODUCCION_REGLAMENTO\nCONTENIDO: El presente reglamento norma la presentación de proyectos de tesis de pregrado conducentes a la obtención del título profesional vía Plataforma de Gestión de la Investigación PGI del Vicerrectorado de Investigación VRI de la Universidad Nacional del Altiplano de Puno UNA PUNO para los estudiantes matriculados y egresados de la Universidad Nacional del Altiplano.",
      "source": "REGLAMENTO FINAL (2)",
      "type": "articulo_reglamento",
      "articulo": "INTRODUCCION_REGLAMENTO",
      "entidad": "general"
    },
    {
      "text": "ARTÍCULO: ETAPAS_PROYECTO_TESIS\nCONTENIDO: Las etapas del proyecto de tesis son carga de proyecto revisión de formato de proyecto revisión por el director de tesis revisión por el subdirector de investigación sorteo de jurados revisión de proyecto dictamen de proyecto de investigación generación de acta de dictamen.",
      "source": "REGLAMENTO FINAL (2)",
      "type": "articulo_reglamento",
      "articulo": "ETAPAS_PROYECTO_TESIS",
      "entidad": "general"
    },
    {
      "text": "ARTÍCULO: ETAPAS_BORRADOR_TESIS\nCONTENIDO: Las etapas del borrador de tesis son habilitación de borrador de tesis carga de borrador de tesis revisión de formato de borrador revisión de borrador por jurados dictamen de borrador de tesis carga de archivos para la sustentación sustentación.",
      "source": "REGLAMENTO FINAL (2)",
      "type": "articulo_reglamento",
      "articulo": "ETAPAS_BORRADOR_TESIS",
      "entidad": "general"
    },
    {
      "text": "ARTÍCULO: CONSIDERACIONES_ADICIONALES\nCONTENIDO: Trabajos desaprobados tienen 30 días hábiles para nuevo trámite. Conflictos con jurados se resuelven mediante informe. Proyectos no defendidos en 2 años + 6 meses ampliación son eliminados. Bachiller puede solicitar eliminación con visto bueno del director. Unidades de investigación deben registrar todo el proceso. Sistema PGI permite nuevos borradores hasta 30 días antes de finalización de semestre. Conflictos se resuelven ante unidad de investigación e Instituto de Investigación. Hechos no contemplados los resuelve el Instituto de Investigación. Custodia de trabajos para derechos de autor. Direcciones y personal administrativo administran la plataforma y orientan al bachiller.",
      "source": "REGLAMENTO FINAL (2)",
      "type": "articulo_reglamento",
      "articulo": "CONSIDERACIONES_ADICIONALES",
      "entidad": "general"
    },
    {
      "text": "FACULTAD: FACULTAD_DE_CIENCIAS_AGRARIAS\nESCUELA: ESCUELA_DE_INGENIERIA_AGRONOMICA\nLÍNEA: MANEJO AGRONÓMICO CULTIVOS\nSUBÍNEAS: Gestión sostenible, manejo agronómico y mejoramiento genético de cultivos; Gestión, manejo y conservación de recursos naturales y medio ambiente; Desarrollo de sistemas agropecuarios; Innovación tecnológica, económica y extensión agraria",
      "source": "sublíneas-investigacion-una-puno",
      "type": "linea_investigacion",
      "facultad": "FACULTAD_DE_CIENCIAS_AGRARIAS",
      "escuela": "ESCUELA_DE_INGENIERIA_AGRONOMICA",
      "entidad": "facultad_escuela",
      "metadata": {
        "linea": "MANEJO AGRONÓMICO CULTIVOS",
        "sublineas": "Gestión sostenible, manejo agronómico y mejoramiento genético de cultivos; Gestión, manejo y conservación de recursos naturales y medio ambiente; Desarrollo de sistemas agropecuarios; Innovación tecnológica, económica y extensión agraria"
      }
    },
    {
      "text": "FACULTAD: FACULTAD_DE_CIENCIAS_AGRARIAS\nESCUELA: ESCUELA_DE_INGENIERIA_AGROINDUSTRIAL\nLÍNEA: INGENIERÍA DE PROCESOS\nSUBÍNEAS: Ingeniería, tecnología y gestión agroindustrial",
      "source": "sublíneas-investigacion-una-puno",
      "type": "linea_investigacion",
      "facultad": "FACULTAD_DE_CIENCIAS_AGRARIAS",
      "escuela": "ESCUELA_DE_INGENIERIA_AGROINDUSTRIAL",
      "entidad": "facultad_escuela",
      "metadata": {
        "linea": "INGENIERÍA DE PROCESOS",
        "sublineas": "Ingeniería, tecnología y gestión agroindustrial"
      }
    },
    {
      "text": "FACULTAD: FACULTAD_DE_CIENCIAS_AGRARIAS\nESCUELA: ESCUELA_DE_INGENIERIA_TOPOGRÁFICA_Y_AGRIMENSURA\nLÍNEA: SISTEMAS DE INFORMACIÓN GEOGRÁFICA\nSUBÍNEAS: Topografía aplicada, geodesia, cartografía y catastro; Teledetección, fotometría y sistemas de información geográfica - SIG; Gestión de riesgos y cambio climático; Planificación y ordenamiento territorial; Geotecnia y pavimentos; Diseño geométrico e infraestructura vial; Hidrología e hidráulica de vías",
      "source": "sublíneas-investigacion-una-puno",
      "type": "linea_investigacion",
      "facultad": "FACULTAD_DE_CIENCIAS_AGRARIAS",
      "escuela": "ESCUELA_DE_INGENIERIA_TOPOGRÁFICA_Y_AGRIMENSURA",
      "entidad": "facultad_escuela",
      "metadata": {
        "linea": "SISTEMAS DE INFORMACIÓN GEOGRÁFICA",
        "sublineas": "Topografía aplicada, geodesia, cartografía y catastro; Teledetección, fotometría y sistemas de información geográfica - SIG; Gestión de riesgos y cambio climático; Planificación y ordenamiento territorial; Geotecnia y pavimentos; Diseño geométrico e infraestructura vial; Hidrología e hidráulica de vías"
      }
    },
    {
      "text": "FACULTAD: FACULTAD_DE_MEDICINA_VETERINARIA_Y_ZOOTECNIA\nESCUELA: ESCUELA_DE_MEDICINA_VETERINARIA_Y_ZOOTECNIA\nLÍNEA: CIENCIA Y PRODUCCIÓN ANIMAL\nSUBÍNEAS: Salud animal; Producción animal; Salud pública; Acuicultura (verificar)",
      "source": "sublíneas-investigacion-una-puno",
      "type": "linea_investigacion",
      "facultad": "FACULTAD_DE_MEDICINA_VETERINARIA_Y_ZOOTECNIA",
      "escuela": "ESCUELA_DE_MEDICINA_VETERINARIA_Y_ZOOTECNIA",
      "entidad": "facultad_escuela",
      "metadata": {
        "linea": "CIENCIA Y PRODUCCIÓN ANIMAL",
        "sublineas": "Salud animal; Producción animal; Salud pública; Acuicultura (verificar)"
      }
    },
    {
      "text": "FACULTAD: FACULTAD_DE_INGENIERIA_ECONOMICA\nESCUELA: ESCUELA_DE_INGENIERIA_ECONOMICA\nLÍNEA: ECONOMÍA Y DESARROLLO\nSUBÍNEAS: Economía de la empresa y mercados; Economía regional y local; Políticas públicas; Gobernabilidad Ciudadanía y Desarrollo Social (Sociologia tambien); Desarrollo Turístico Regional (Turismo)",
      "source": "sublíneas-investigacion-una-puno",
      "type": "linea_investigacion",
      "facultad": "FACULTAD_DE_INGENIERIA_ECONOMICA",
      "escuela": "ESCUELA_DE_INGENIERIA_ECONOMICA",
      "entidad": "facultad_escuela",
      "metadata": {
        "linea": "ECONOMÍA Y DESARROLLO",
        "sublineas": "Economía de la empresa y mercados; Economía regional y local; Políticas públicas; Gobernabilidad Ciudadanía y Desarrollo Social (Sociologia tambien); Desarrollo Turístico Regional (Turismo)"
      }
    },
    {
      "text": "FACULTAD: FACULTAD_DE_INGENIERIA_ECONOMICA\nESCUELA: ESCUELA_DE_ADMINISTRACION\nLÍNEA: ADMINISTRACIÓN Y MARKETING\nSUBÍNEAS: Administración de finanzas; Administración de procesos organizacionales; Administración de emprendimientos; Administración general; Administración de recursos humanos; Administración de marketing y negocios internacionales; Administración pública; Administración de Empresas Turísticas (revisar)",
      "source": "sublíneas-investigacion-una-puno",
      "type": "linea_investigacion",
      "facultad": "FACULTAD_DE_INGENIERIA_ECONOMICA",
      "escuela": "ESCUELA_DE_ADMINISTRACION",
      "entidad": "facultad_escuela",
      "metadata": {
        "linea": "ADMINISTRACIÓN Y MARKETING",
        "sublineas": "Administración de finanzas; Administración de procesos organizacionales; Administración de emprendimientos; Administración general; Administración de recursos humanos; Administración de marketing y negocios internacionales; Administración pública; Administración de Empresas Turísticas (revisar)"
      }
    },
    {
      "text": "FACULTAD: FACULTAD_DE_CIENCIAS_CONTABLES_Y_ADMINISTRATIVAS\nESCUELA: ESCUELA_DE_CIENCIAS_CONTABLES\nLÍNEA: AUDITORÍA, COSTOS Y FINANZAS\nSUBÍNEAS: Contabilidad y auditoría; Finanzas y gestión; Tributación; Gestión pública",
      "source": "sublíneas-investigacion-una-puno",
      "type": "linea_investigacion",
      "facultad": "FACULTAD_DE_CIENCIAS_CONTABLES_Y_ADMINISTRATIVAS",
      "escuela": "ESCUELA_DE_CIENCIAS_CONTABLES",
      "entidad": "facultad_escuela",
      "metadata": {
        "linea": "AUDITORÍA, COSTOS Y FINANZAS",
        "sublineas": "Contabilidad y auditoría; Finanzas y gestión; Tributación; Gestión pública"
      }
    },
    {
      "text": "FACULTAD: FACULTAD_DE_ENFERMERIA\nESCUELA: ESCUELA_DE_ENFERMERIA\nLÍNEA: SALUD PÚBLICA\nSUBÍNEAS: Salud del recién nacido, niño, escolar y adolescente; Salud del adulto y salud de la mujer; Gerencia y gestión en salud, salud familiar y comunitaria",
      "source": "sublíneas-investigacion-una-puno",
      "type": "linea_investigacion",
      "facultad": "FACULTAD_DE_ENFERMERIA",
      "escuela": "ESCUELA_DE_ENFERMERIA",
      "entidad": "facultad_escuela",
      "metadata": {
        "linea": "SALUD PÚBLICA",
        "sublineas": "Salud del recién nacido, niño, escolar y adolescente; Salud del adulto y salud de la mujer; Gerencia y gestión en salud, salud familiar y comunitaria"
      }
    },
    {
      "text": "FACULTAD: FACULTAD_DE_TRABAJO_SOCIAL\nESCUELA: ESCUELA_DE_TRABAJO_SOCIAL\nLÍNEA: SOCIEDAD, CULTURA Y COMUNICACIÓN\nSUBÍNEAS: Desarrollo humano y calidad de vida; Familias: realidades, cambio y dinámicas de intervención; Derechos humanos y fortalecimiento democrático",
      "source": "sublíneas-investigacion-una-puno",
      "type": "linea_investigacion",
      "facultad": "FACULTAD_DE_TRABAJO_SOCIAL",
      "escuela": "ESCUELA_DE_TRABAJO_SOCIAL",
      "entidad": "facultad_escuela",
      "metadata": {
        "linea": "SOCIEDAD, CULTURA Y COMUNICACIÓN",
        "sublineas": "Desarrollo humano y calidad de vida; Familias: realidades, cambio y dinámicas de intervención; Derechos humanos y fortalecimiento democrático"
      }
    },
    {
      "text": "FACULTAD: FACULTAD_DE_CIENCIAS_SOCIALES\nESCUELA: ESCUELA_DE_ANTROPOLOGIA\nLÍNEA: GESTIÓN Y RESPONSABILIDAD SOCIAL\nSUBÍNEAS: Cultura andina, sociedad y medioambiente; Antropología jurídica y forense biológica-cultural (REVISAR)",
      "source": "sublíneas-investigacion-una-puno",
      "type": "linea_investigacion",
      "facultad": "FACULTAD_DE_CIENCIAS_SOCIALES",
      "escuela": "ESCUELA_DE_ANTROPOLOGIA",
      "entidad": "facultad_escuela",
      "metadata": {
        "linea": "GESTIÓN Y RESPONSABILIDAD SOCIAL",
        "sublineas": "Cultura andina, sociedad y medioambiente; Antropología jurídica y forense biológica-cultural (REVISAR)"
      }
    },
    {
      "text": "FACULTAD: FACULTAD_DE_CIENCIAS_SOCIALES\nESCUELA: ESCUELA_DE_ARTE\nLÍNEA: ARTE Y MÚSICA\nSUBÍNEAS: Danza: revaloración de las danzas étnicas de nuestro contexto para la generación de conocimiento, cultura Y memoria histórica; Música: Análisis e interpretación de la producción musical; Música: Innovaciones y aplicación de tecnologías en la producción musical; Artes Plásticas: Creación plástica en base a las técnicas tradicionales Y Tecnologías actuales, considerando aspectos filosóficos y teóricos; Artes Plásticas: Gestión y administración de la labor artística Enfatizando Los Nuevos Escenarios Plásticos",
      "source": "sublíneas-investigacion-una-puno",
      "type": "linea_investigacion",
      "facultad": "FACULTAD_DE_CIENCIAS_SOCIALES",
      "escuela": "ESCUELA_DE_ARTE",
      "entidad": "facultad_escuela",
      "metadata": {
        "linea": "ARTE Y MÚSICA",
        "sublineas": "Danza: revaloración de las danzas étnicas de nuestro contexto para la generación de conocimiento, cultura Y memoria histórica; Música: Análisis e interpretación de la producción musical; Música: Innovaciones y aplicación de tecnologías en la producción musical; Artes Plásticas: Creación plástica en base a las técnicas tradicionales Y Tecnologías actuales, considerando aspectos filosóficos y teóricos; Artes Plásticas: Gestión y administración de la labor artística Enfatizando Los Nuevos Escenarios Plásticos"
      }
    },
    {
      "text": "FACULTAD: FACULTAD_DE_CIENCIAS_SOCIALES\nESCUELA: ESCUELA_DE_CIENCIAS_DE_LA_COMUNICACION_SOCIAL\nLÍNEA: SOCIEDAD, CULTURA Y COMUNICACIÓN\nSUBÍNEAS: Comunicación sociocultural y desarrollo; Comunicación organizacional, marketing y publicidad; Medios de comunicación y periodismo",
      "source": "sublíneas-investigacion-una-puno",
      "type": "linea_investigacion",
      "facultad": "FACULTAD_DE_CIENCIAS_SOCIALES",
      "escuela": "ESCUELA_DE_CIENCIAS_DE_LA_COMUNICACION_SOCIAL",
      "entidad": "facultad_escuela",
      "metadata": {
        "linea": "SOCIEDAD, CULTURA Y COMUNICACIÓN",
        "sublineas": "Comunicación sociocultural y desarrollo; Comunicación organizacional, marketing y publicidad; Medios de comunicación y periodismo"
      }
    },
    {
      "text": "FACULTAD: FACULTAD_DE_CIENCIAS_SOCIALES\nESCUELA: ESCUELA_DE_SOCIOLOGIA\nLÍNEA: SOCIEDAD, CULTURA Y COMUNICACIÓN / GESTIÓN Y RESPONSABILIDAD SOCIAL\nSUBÍNEAS: Análisis de procesos sociales; Organizaciones, liderazgo y gestión organizacional; Gobernabilidad, ciudadanía y desarrollo social; Sociolingüística e interculturalidad; Política, gestión pública y planificación; Institucionalidad, conflictos y gestión ambiental",
      "source": "sublíneas-investigacion-una-puno",
      "type": "linea_investigacion",
      "facultad": "FACULTAD_DE_CIENCIAS_SOCIALES",
      "escuela": "ESCUELA_DE_SOCIOLOGIA",
      "entidad": "facultad_escuela",
      "metadata": {
        "linea": "SOCIEDAD, CULTURA Y COMUNICACIÓN / GESTIÓN Y RESPONSABILIDAD SOCIAL",
        "sublineas": "Análisis de procesos sociales; Organizaciones, liderazgo y gestión organizacional; Gobernabilidad, ciudadanía y desarrollo social; Sociolingüística e interculturalidad; Política, gestión pública y planificación; Institucionalidad, conflictos y gestión ambiental"
      }
    },
    {
      "text": "FACULTAD: FACULTAD_DE_CIENCIAS_SOCIALES\nESCUELA: ESCUELA_DE_TURISMO\nLÍNEA: ADMINISTRACIÓN Y MARKETING / ECONOMÍA Y DESARROLLO / GESTIÓN Y RESPONSABILIDAD SOCIAL\nSUBÍNEAS: Administración de empresas turísticas; Desarrollo turístico regional; Gestión de destinos turísticos; Gestión de emprendimientos y negocios turísticos",
      "source": "sublíneas-investigacion-una-puno",
      "type": "linea_investigacion",
      "facultad": "FACULTAD_DE_CIENCIAS_SOCIALES",
      "escuela": "ESCUELA_DE_TURISMO",
      "entidad": "facultad_escuela",
      "metadata": {
        "linea": "ADMINISTRACIÓN Y MARKETING / ECONOMÍA Y DESARROLLO / GESTIÓN Y RESPONSABILIDAD SOCIAL",
        "sublineas": "Administración de empresas turísticas; Desarrollo turístico regional; Gestión de destinos turísticos; Gestión de emprendimientos y negocios turísticos"
      }
    },
    {
      "text": "FACULTAD: FACULTAD_DE_CIENCIAS_SOCIALES\nESCUELA: ESCUELA_DE_PSICOLOGIA\nLÍNEA: (En proceso de definición de sublíneas específicas)\nSUBÍNEAS: (En proceso de definición de sublíneas específicas)",
      "source": "sublíneas-investigacion-una-puno",
      "type": "linea_investigacion",
      "facultad": "FACULTAD_DE_CIENCIAS_SOCIALES",
      "escuela": "ESCUELA_DE_PSICOLOGIA",
      "entidad": "facultad_escuela",
      "metadata": {
        "linea": "(En proceso de definición de sublíneas específicas)",
        "sublineas": "(En proceso de definición de sublíneas específicas)"
      }
    },
    {
      "text": "FACULTAD: FACULTAD_DE_INGENIERIA_DE_MINAS\nESCUELA: ESCUELA_DE_INGENIERIA_DE_MINAS\nLÍNEA: GEOLOGÍA, MINAS Y METALURGIA\nSUBÍNEAS: Sistemas de extracción de recursos minerales; Geotecnia y estabilidad de minas; Minería sostenible y medio ambiente; Tecnologías de la información en minería",
      "source": "sublíneas-investigacion-una-puno",
      "type": "linea_investigacion",
      "facultad": "FACULTAD_DE_INGENIERIA_DE_MINAS",
      "escuela": "ESCUELA_DE_INGENIERIA_DE_MINAS",
      "entidad": "facultad_escuela",
      "metadata": {
        "linea": "GEOLOGÍA, MINAS Y METALURGIA",
        "sublineas": "Sistemas de extracción de recursos minerales; Geotecnia y estabilidad de minas; Minería sostenible y medio ambiente; Tecnologías de la información en minería"
      }
    },
    {
      "text": "FACULTAD: FACULTAD_DE_CIENCIAS_JURIDICAS_Y_POLITICAS\nESCUELA: ESCUELA_DE_DERECHO\nLÍNEA: DERECHO\nSUBÍNEAS: Derecho penal; Derecho administrativo; Derecho laboral; Derecho constitucional; Derecho civil; Teoría del derecho; Derechos humanos y fortalecimiento democrático (revisar)",
      "source": "sublíneas-investigacion-una-puno",
      "type": "linea_investigacion",
      "facultad": "FACULTAD_DE_CIENCIAS_JURIDICAS_Y_POLITICAS",
      "escuela": "ESCUELA_DE_DERECHO",
      "entidad": "facultad_escuela",
      "metadata": {
        "linea": "DERECHO",
        "sublineas": "Derecho penal; Derecho administrativo; Derecho laboral; Derecho constitucional; Derecho civil; Teoría del derecho; Derechos humanos y fortalecimiento democrático (revisar)"
      }
    },
    {
      "text": "FACULTAD: FACULTAD_DE_INGENIERIA_QUIMICA\nESCUELA: ESCUELA_DE_INGENIERIA_QUIMICA\nLÍNEA: INGENIERÍA DE PROCESOS / ALIMENTACIÓN Y NUTRICIÓN HUMANA / RECURSOS NATURALES Y MEDIO AMBIENTE\nSUBÍNEAS: Desarrollo de operaciones, procesos industriales y automatización; Recuperación, conservación y transformación de recursos naturales; Seguridad industrial y ambiental; Tecnologías ambientales y energías renovables; Procesamiento de alimentos",
      "source": "sublíneas-investigacion-una-puno",
      "type": "linea_investigacion",
      "facultad": "FACULTAD_DE_INGENIERIA_QUIMICA",
      "escuela": "ESCUELA_DE_INGENIERIA_QUIMICA",
      "entidad": "facultad_escuela",
      "metadata": {
        "linea": "INGENIERÍA DE PROCESOS / ALIMENTACIÓN Y NUTRICIÓN HUMANA / RECURSOS NATURALES Y MEDIO AMBIENTE",
        "sublineas": "Desarrollo de operaciones, procesos industriales y automatización; Recuperación, conservación y transformación de recursos naturales; Seguridad industrial y ambiental; Tecnologías ambientales y energías renovables; Procesamiento de alimentos"
      }
    },
    {
      "text": "FACULTAD: FACULTAD_DE_CIENCIAS_BIOLOGICAS\nESCUELA: ESCUELA_DE_CIENCIAS_BIOLOGICAS_ECOLOGIA\nLÍNEA: CIENCIA Y PRODUCCIÓN ANIMAL / RECURSOS NATURALES Y MEDIO AMBIENTE / CIENCIAS DE LA SALUD\nSUBÍNEAS: Acuicultura; Conservación y aprovechamiento de recursos naturales; Calidad ambiental; Diagnóstico y epidemiología; Microbiología aplicada y biotecnología en salud y medio ambiente",
      "source": "sublíneas-investigacion-una-puno",
      "type": "linea_investigacion",
      "facultad": "FACULTAD_DE_CIENCIAS_BIOLOGICAS",
      "escuela": "ESCUELA_DE_CIENCIAS_BIOLOGICAS_ECOLOGIA",
      "entidad": "facultad_escuela",
      "metadata": {
        "linea": "CIENCIA Y PRODUCCIÓN ANIMAL / RECURSOS NATURALES Y MEDIO AMBIENTE / CIENCIAS DE LA SALUD",
        "sublineas": "Acuicultura; Conservación y aprovechamiento de recursos naturales; Calidad ambiental; Diagnóstico y epidemiología; Microbiología aplicada y biotecnología en salud y medio ambiente"
      }
    },
    {
      "text": "FACULTAD: FACULTAD_DE_CIENCIAS_BIOLOGICAS\nESCUELA: ESCUELA_DE_CIENCIAS_BIOLOGICAS_PESQUERIA\nLÍNEA: CIENCIA Y PRODUCCIÓN ANIMAL / RECURSOS NATURALES Y MEDIO AMBIENTE\nSUBÍNEAS: Acuicultura; Conservación y aprovechamiento de recursos naturales; Calidad ambiental",
      "source": "sublíneas-investigacion-una-puno",
      "type": "linea_investigacion",
      "facultad": "FACULTAD_DE_CIENCIAS_BIOLOGICAS",
      "escuela": "ESCUELA_DE_CIENCIAS_BIOLOGICAS_PESQUERIA",
      "entidad": "facultad_escuela",
      "metadata": {
        "linea": "CIENCIA Y PRODUCCIÓN ANIMAL / RECURSOS NATURALES Y MEDIO AMBIENTE",
        "sublineas": "Acuicultura; Conservación y aprovechamiento de recursos naturales; Calidad ambiental"
      }
    },
    {
      "text": "FACULTAD: FACULTAD_DE_CIENCIAS_BIOLOGICAS\nESCUELA: ESCUELA_DE_CIENCIAS_BIOLOGICAS_MICROBIOLOGIA\nLÍNEA: CIENCIAS DE LA SALUD / RECURSOS NATURALES Y MEDIO AMBIENTE\nSUBÍNEAS: Diagnóstico y epidemiología; Microbiología aplicada y biotecnología en salud y medio ambiente; Calidad ambiental",
      "source": "sublíneas-investigacion-una-puno",
      "type": "linea_investigacion",
      "facultad": "FACULTAD_DE_CIENCIAS_BIOLOGICAS",
      "escuela": "ESCUELA_DE_CIENCIAS_BIOLOGICAS_MICROBIOLOGIA",
      "entidad": "facultad_escuela",
      "metadata": {
        "linea": "CIENCIAS DE LA SALUD / RECURSOS NATURALES Y MEDIO AMBIENTE",
        "sublineas": "Diagnóstico y epidemiología; Microbiología aplicada y biotecnología en salud y medio ambiente; Calidad ambiental"
      }
    },
    {
      "text": "FACULTAD: FACULTAD_DE_CIENCIAS_DE_LA_EDUCACION\nESCUELA: ESCUELA_DE_EDUCACION_FISICA\nLÍNEA: CIENCIAS DEL DEPORTE Y EDUCACIÓN FÍSICA\nSUBÍNEAS: Psicomotricidad; Educación física; Deporte y recreación; Ciencias del deporte; Promoción de la salud",
      "source": "sublíneas-investigacion-una-puno",
      "type": "linea_investigacion",
      "facultad": "FACULTAD_DE_CIENCIAS_DE_LA_EDUCACION",
      "escuela": "ESCUELA_DE_EDUCACION_FISICA",
      "entidad": "facultad_escuela",
      "metadata": {
        "linea": "CIENCIAS DEL DEPORTE Y EDUCACIÓN FÍSICA",
        "sublineas": "Psicomotricidad; Educación física; Deporte y recreación; Ciencias del deporte; Promoción de la salud"
      }
    },
    {
      "text": "FACULTAD: FACULTAD_DE_CIENCIAS_DE_LA_EDUCACION\nESCUELA: ESCUELA_DE_EDUCACION_INICIAL\nLÍNEA: EDUCACIÓN Y DINÁMICA EDUCATIVA / GESTIÓN Y RESPONSABILIDAD SOCIAL\nSUBÍNEAS: Perspectivas teóricas de la educación en la primera infancia; Gestión curricular en la primera infancia; Responsabilidad social de la educación",
      "source": "sublíneas-investigacion-una-puno",
      "type": "linea_investigacion",
      "facultad": "FACULTAD_DE_CIENCIAS_DE_LA_EDUCACION",
      "escuela": "ESCUELA_DE_EDUCACION_INICIAL",
      "entidad": "facultad_escuela",
      "metadata": {
        "linea": "EDUCACIÓN Y DINÁMICA EDUCATIVA / GESTIÓN Y RESPONSABILIDAD SOCIAL",
        "sublineas": "Perspectivas teóricas de la educación en la primera infancia; Gestión curricular en la primera infancia; Responsabilidad social de la educación"
      }
    },
    {
      "text": "FACULTAD: FACULTAD_DE_CIENCIAS_DE_LA_EDUCACION\nESCUELA: ESCUELA_DE_EDUCACION_PRIMARIA\nLÍNEA: EDUCACIÓN Y DINÁMICA EDUCATIVA / GESTIÓN Y RESPONSABILIDAD SOCIAL\nSUBÍNEAS: Perspectivas teóricas de la educación; Gestión curricular; Responsabilidad social de la educación",
      "source": "sublíneas-investigacion-una-puno",
      "type": "linea_investigacion",
      "facultad": "FACULTAD_DE_CIENCIAS_DE_LA_EDUCACION",
      "escuela": "ESCUELA_DE_EDUCACION_PRIMARIA",
      "entidad": "facultad_escuela",
      "metadata": {
        "linea": "EDUCACIÓN Y DINÁMICA EDUCATIVA / GESTIÓN Y RESPONSABILIDAD SOCIAL",
        "sublineas": "Perspectivas teóricas de la educación; Gestión curricular; Responsabilidad social de la educación"
      }
    },
    {
      "text": "FACULTAD: FACULTAD_DE_CIENCIAS_DE_LA_EDUCACION\nESCUELA: ESCUELA_DE_INGENIERIA_GEOLOGICA\nLÍNEA: GEOLOGÍA, MINAS Y METALURGIA\nSUBÍNEAS: Seguridad y medio ambiente; Ingeniería geotécnica; Geología regional; Geología de minas",
      "source": "sublíneas-investigacion-una-puno",
      "type": "linea_investigacion",
      "facultad": "FACULTAD_DE_CIENCIAS_DE_LA_EDUCACION",
      "escuela": "ESCUELA_DE_INGENIERIA_GEOLOGICA",
      "entidad": "facultad_escuela",
      "metadata": {
        "linea": "GEOLOGÍA, MINAS Y METALURGIA",
        "sublineas": "Seguridad y medio ambiente; Ingeniería geotécnica; Geología regional; Geología de minas"
      }
    },
    {
      "text": "FACULTAD: FACULTAD_DE_INGENIERIA_GEOLOGICA_Y_METALURGICA\nESCUELA: ESCUELA_DE_INGENIERIA_METALURGICA\nLÍNEA: GEOLOGÍA, MINAS Y METALURGIA\nSUBÍNEAS: Metalurgia extractiva; Metalurgia transformativa; Medio ambiente y seguridad en procesos metalúrgicos",
      "source": "sublíneas-investigacion-una-puno",
      "type": "linea_investigacion",
      "facultad": "FACULTAD_DE_INGENIERIA_GEOLOGICA_Y_METALURGICA",
      "escuela": "ESCUELA_DE_INGENIERIA_METALURGICA",
      "entidad": "facultad_escuela",
      "metadata": {
        "linea": "GEOLOGÍA, MINAS Y METALURGIA",
        "sublineas": "Metalurgia extractiva; Metalurgia transformativa; Medio ambiente y seguridad en procesos metalúrgicos"
      }
    },
    {
      "text": "FACULTAD: FACULTAD_DE_INGENIERIA_ESTADISTICA_E_INFORMATICA\nESCUELA: ESCUELA_DE_INGENIERIA_ESTADISTICA_E_INFORMATICA\nLÍNEA: ESTADÍSTICA E INVESTIGACIÓN\nSUBÍNEAS: Ingeniería de software e inteligencia artificial; Modelos predictivos uni y multivariantes; Base de datos y sistemas de información; Análisis multivariado, big data, minería de datos e investigación de mercados",
      "source": "sublíneas-investigacion-una-puno",
      "type": "linea_investigacion",
      "facultad": "FACULTAD_DE_INGENIERIA_ESTADISTICA_E_INFORMATICA",
      "escuela": "ESCUELA_DE_INGENIERIA_ESTADISTICA_E_INFORMATICA",
      "entidad": "facultad_escuela",
      "metadata": {
        "linea": "ESTADÍSTICA E INVESTIGACIÓN",
        "sublineas": "Ingeniería de software e inteligencia artificial; Modelos predictivos uni y multivariantes; Base de datos y sistemas de información; Análisis multivariado, big data, minería de datos e investigación de mercados"
      }
    },
    {
      "text": "FACULTAD: FACULTAD_DE_INGENIERIA_CIVIL_Y_ARQUITECTURA\nESCUELA: ESCUELA_DE_INGENIERIA_CIVIL\nLÍNEA: INFRAESTRUCTURA Y CONSTRUCCIONES\nSUBÍNEAS: Construcción y gerencia; Geotecnia; Hidráulica y medio ambiente; Análisis y diseño estructural; Transportes y gestión vial",
      "source": "sublíneas-investigacion-una-puno",
      "type": "linea_investigacion",
      "facultad": "FACULTAD_DE_INGENIERIA_CIVIL_Y_ARQUITECTURA",
      "escuela": "ESCUELA_DE_INGENIERIA_CIVIL",
      "entidad": "facultad_escuela",
      "metadata": {
        "linea": "INFRAESTRUCTURA Y CONSTRUCCIONES",
        "sublineas": "Construcción y gerencia; Geotecnia; Hidráulica y medio ambiente; Análisis y diseño estructural; Transportes y gestión vial"
      }
    },
    {
      "text": "FACULTAD: FACULTAD_DE_INGENIERIA_CIVIL_Y_ARQUITECTURA\nESCUELA: ESCUELA_DE_ARQUITECTURA_Y_URBANISMO\nLÍNEA: ARQUITECTURA Y URBANISMO\nSUBÍNEAS: Arquitectura, teoría y diseño arquitectónico sostenible; Planificación urbana y desarrollo territorial sostenible; Tecnología, gestión e innovación en la edificación; Patrimonio arquitectónico y arquitectura social",
      "source": "sublíneas-investigacion-una-puno",
      "type": "linea_investigacion",
      "facultad": "FACULTAD_DE_INGENIERIA_CIVIL_Y_ARQUITECTURA",
      "escuela": "ESCUELA_DE_ARQUITECTURA_Y_URBANISMO",
      "entidad": "facultad_escuela",
      "metadata": {
        "linea": "ARQUITECTURA Y URBANISMO",
        "sublineas": "Arquitectura, teoría y diseño arquitectónico sostenible; Planificación urbana y desarrollo territorial sostenible; Tecnología, gestión e innovación en la edificación; Patrimonio arquitectónico y arquitectura social"
      }
    },
    {
      "text": "FACULTAD: FACULTAD_DE_INGENIERIA_AGRICOLA\nESCUELA: ESCUELA_DE_INGENIERIA_AGRICOLA\nLÍNEA: INFRAESTRUCTURA Y CONSTRUCCIONES / RECURSOS NATURALES Y MEDIO AMBIENTE\nSUBÍNEAS: Recursos hídricos; Ingeniería de infraestructura rural; Ordenamiento territorial y medio ambiente",
      "source": "sublíneas-investigacion-una-puno",
      "type": "linea_investigacion",
      "facultad": "FACULTAD_DE_INGENIERIA_AGRICOLA",
      "escuela": "ESCUELA_DE_INGENIERIA_AGRICOLA",
      "entidad": "facultad_escuela",
      "metadata": {
        "linea": "INFRAESTRUCTURA Y CONSTRUCCIONES / RECURSOS NATURALES Y MEDIO AMBIENTE",
        "sublineas": "Recursos hídricos; Ingeniería de infraestructura rural; Ordenamiento territorial y medio ambiente"
      }
    },
    {
      "text": "FACULTAD: FACULTAD_DE_CIENCIAS_DE_LA_SALUD\nESCUELA: ESCUELA_DE_NUTRICION_HUMANA\nLÍNEA: ALIMENTACIÓN Y NUTRICIÓN HUMANA\nSUBÍNEAS: Atención nutricional a personas sanas y enfermas en las diferentes etapas de la vida; Promoción de salud de las personas; Formulación, evaluación y gestión de proyectos y empresas con alimentos, nutrición y salud; Innovación, análisis y control de los alimentos en el sistema alimentario",
      "source": "sublíneas-investigacion-una-puno",
      "type": "linea_investigacion",
      "facultad": "FACULTAD_DE_CIENCIAS_DE_LA_SALUD",
      "escuela": "ESCUELA_DE_NUTRICION_HUMANA",
      "entidad": "facultad_escuela",
      "metadata": {
        "linea": "ALIMENTACIÓN Y NUTRICIÓN HUMANA",
        "sublineas": "Atención nutricional a personas sanas y enfermas en las diferentes etapas de la vida; Promoción de salud de las personas; Formulación, evaluación y gestión de proyectos y empresas con alimentos, nutrición y salud; Innovación, análisis y control de los alimentos en el sistema alimentario"
      }
    },
    {
      "text": "FACULTAD: FACULTAD_DE_CIENCIAS_DE_LA_SALUD\nESCUELA: ESCUELA_DE_ODONTOLOGIA\nLÍNEA: CIENCIAS DE LA SALUD\nSUBÍNEAS: Salud pública y ocupacional; Biología, crecimiento y desarrollo craneofacial; Diagnóstico, tratamiento y rehabilitación del sistema estomatognático",
      "source": "sublíneas-investigacion-una-puno",
      "type": "linea_investigacion",
      "facultad": "FACULTAD_DE_CIENCIAS_DE_LA_SALUD",
      "escuela": "ESCUELA_DE_ODONTOLOGIA",
      "entidad": "facultad_escuela",
      "metadata": {
        "linea": "CIENCIAS DE LA SALUD",
        "sublineas": "Salud pública y ocupacional; Biología, crecimiento y desarrollo craneofacial; Diagnóstico, tratamiento y rehabilitación del sistema estomatognático"
      }
    },
    {
      "text": "FACULTAD: FACULTAD_DE_INGENIERIA_MECANICA_ELECTRICA_ELECTRONICA_Y_SISTEMAS\nESCUELA: ESCUELA_DE_INGENIERIA_ELECTRONICA\nLÍNEA: MECÁNICA - ELÉCTRICA / SISTEMAS, COMPUTACIÓN E INFORMÁTICA\nSUBÍNEAS: Automatización e instrumentación; Telecomunicaciones y redes de datos; Microelectrónica (revisar); Robótica (revisar)",
      "source": "sublíneas-investigacion-una-puno",
      "type": "linea_investigacion",
      "facultad": "FACULTAD_DE_INGENIERIA_MECANICA_ELECTRICA_ELECTRONICA_Y_SISTEMAS",
      "escuela": "ESCUELA_DE_INGENIERIA_ELECTRONICA",
      "entidad": "facultad_escuela",
      "metadata": {
        "linea": "MECÁNICA - ELÉCTRICA / SISTEMAS, COMPUTACIÓN E INFORMÁTICA",
        "sublineas": "Automatización e instrumentación; Telecomunicaciones y redes de datos; Microelectrónica (revisar); Robótica (revisar)"
      }
    },
    {
      "text": "FACULTAD: FACULTAD_DE_INGENIERIA_MECANICA_ELECTRICA_ELECTRONICA_Y_SISTEMAS\nESCUELA: ESCUELA_DE_INGENIERIA_MECANICA_ELECTRICA\nLÍNEA: MECÁNICA - ELÉCTRICA / RECURSOS NATURALES Y MEDIO AMBIENTE\nSUBÍNEAS: Control de procesos; Energías renovables; Ingeniería eléctrica; Ingeniería mecánica; Aplicaciones energéticas (revisar)",
      "source": "sublíneas-investigacion-una-puno",
      "type": "linea_investigacion",
      "facultad": "FACULTAD_DE_INGENIERIA_MECANICA_ELECTRICA_ELECTRONICA_Y_SISTEMAS",
      "escuela": "ESCUELA_DE_INGENIERIA_MECANICA_ELECTRICA",
      "entidad": "facultad_escuela",
      "metadata": {
        "linea": "MECÁNICA - ELÉCTRICA / RECURSOS NATURALES Y MEDIO AMBIENTE",
        "sublineas": "Control de procesos; Energías renovables; Ingeniería eléctrica; Ingeniería mecánica; Aplicaciones energéticas (revisar)"
      }
    },
    {
      "text": "FACULTAD: FACULTAD_DE_INGENIERIA_MECANICA_ELECTRICA_ELECTRONICA_Y_SISTEMAS\nESCUELA: ESCUELA_DE_INGENIERIA_DE_SISTEMAS\nLÍNEA: SISTEMAS, COMPUTACIÓN E INFORMÁTICA\nSUBÍNEAS: Ingeniería de software, bases de datos e inteligencia de negocios; Inteligencia artificial, sistemas computacionales y sistemas bioinspirados; Desarrollo, gestión, seguridad y auditoría de sistemas de información; Nuevas tecnologías - informática, educación y sociedad; Teoría de sistemas, administración de sistemas, sistemas distribuidos, redes y telemática",
      "source": "sublíneas-investigacion-una-puno",
      "type": "linea_investigacion",
      "facultad": "FACULTAD_DE_INGENIERIA_MECANICA_ELECTRICA_ELECTRONICA_Y_SISTEMAS",
      "escuela": "ESCUELA_DE_INGENIERIA_DE_SISTEMAS",
      "entidad": "facultad_escuela",
      "metadata": {
        "linea": "SISTEMAS, COMPUTACIÓN E INFORMÁTICA",
        "sublineas": "Ingeniería de software, bases de datos e inteligencia de negocios; Inteligencia artificial, sistemas computacionales y sistemas bioinspirados; Desarrollo, gestión, seguridad y auditoría de sistemas de información; Nuevas tecnologías - informática, educación y sociedad; Teoría de sistemas, administración de sistemas, sistemas distribuidos, redes y telemática"
      }
    },
    {
      "text": "FACULTAD: FACULTAD_DE_INGENIERIA_MECANICA_ELECTRICA_ELECTRONICA_Y_SISTEMAS\nESCUELA: ESCUELA_DE_INGENIERIA_DE_TELECOMUNICACIONES\nLÍNEA: (En proceso de definición de sublíneas específicas)\nSUBÍNEAS: (En proceso de definición de sublíneas específicas)",
      "source": "sublíneas-investigacion-una-puno",
      "type": "linea_investigacion",
      "facultad": "FACULTAD_DE_INGENIERIA_MECANICA_ELECTRICA_ELECTRONICA_Y_SISTEMAS",
      "escuela": "ESCUELA_DE_INGENIERIA_DE_TELECOMUNICACIONES",
      "entidad": "facultad_escuela",
      "metadata": {
        "linea": "(En proceso de definición de sublíneas específicas)",
        "sublineas": "(En proceso de definición de sublíneas específicas)"
      }
    },
    {
      "text": "FACULTAD: FACULTAD_DE_INGENIERIA_MECANICA_ELECTRICA_ELECTRONICA_Y_SISTEMAS\nESCUELA: ESCUELA_DE_INTELIGENCIA_ARTIFICIAL_Y_CIENCIA_DE_DATOS\nLÍNEA: (En proceso de definición de sublíneas específicas)\nSUBÍNEAS: (En proceso de definición de sublíneas específicas)",
      "source": "sublíneas-investigacion-una-puno",
      "type": "linea_investigacion",
      "facultad": "FACULTAD_DE_INGENIERIA_MECANICA_ELECTRICA_ELECTRONICA_Y_SISTEMAS",
      "escuela": "ESCUELA_DE_INTELIGENCIA_ARTIFICIAL_Y_CIENCIA_DE_DATOS",
      "entidad": "facultad_escuela",
      "metadata": {
        "linea": "(En proceso de definición de sublíneas específicas)",
        "sublineas": "(En proceso de definición de sublíneas específicas)"
      }
    },
    {
      "text": "FACULTAD: FACULTAD_DE_MEDICINA_HUMANA\nESCUELA: ESCUELA_DE_MEDICINA_HUMANA\nLÍNEA: CIENCIAS DE LA SALUD\nSUBÍNEAS: Ciencias médicas básicas; Ciencias médicas clínicas; Medicina de altura",
      "source": "sublíneas-investigacion-una-puno",
      "type": "linea_investigacion",
      "facultad": "FACULTAD_DE_MEDICINA_HUMANA",
      "escuela": "ESCUELA_DE_MEDICINA_HUMANA",
      "entidad": "facultad_escuela",
      "metadata": {
        "linea": "CIENCIAS DE LA SALUD",
        "sublineas": "Ciencias médicas básicas; Ciencias médicas clínicas; Medicina de altura"
      }
    },
    {
      "text": "FACULTAD: FACULTAD_DE_CIENCIAS_ADMINISTRATIVAS_Y_HUMANAS\nESCUELA: ESCUELA_DE_ADMINISTRACION\nLÍNEA: ADMINISTRACIÓN Y MARKETING\nSUBÍNEAS: Administración de finanzas; Administración de procesos organizacionales; Administración de emprendimientos; Administración general; Administración de recursos humanos; Administración de marketing y negocios internacionales; Administración pública",
      "source": "sublíneas-investigacion-una-puno",
      "type": "linea_investigacion",
      "facultad": "FACULTAD_DE_CIENCIAS_ADMINISTRATIVAS_Y_HUMANAS",
      "escuela": "ESCUELA_DE_ADMINISTRACION",
      "entidad": "facultad_escuela",
      "metadata": {
        "linea": "ADMINISTRACIÓN Y MARKETING",
        "sublineas": "Administración de finanzas; Administración de procesos organizacionales; Administración de emprendimientos; Administración general; Administración de recursos humanos; Administración de marketing y negocios internacionales; Administración pública"
      }
    }
  ],
  "model_name": "paraphrase-multilingual-MiniLM-L12-v2",
  "total_docs": 98,
  "dimension": 384,
  "chunk_types": {
    "coordinador": 20,
    "etapa_proceso": 3,
    "actor_proceso": 8,
    "pregunta_frecuente": 24,
    "articulo_reglamento": 4,
    "linea_investigacion": 39
  },
  "faculty_counts": {
    "FACULTAD_DE_CIENCIAS_AGRARIAS": 4,
    "FACULTAD_DE_MEDICINA_VETERINARIA_Y_ZOOTECNIA": 2,
    "FACULTAD_DE_INGENIERIA_ECONOMICA": 3,
    "FACULTAD_DE_CIENCIAS_CONTABLES_Y_ADMINISTRATIVAS": 2,
    "FACULTAD_DE_TRABAJO_SOCIAL": 2,
    "FACULTAD_DE_ENFERMERIA": 2,
    "FACULTAD_DE_CIENCIAS_SOCIALES": 7,
    "FACULTAD_DE_INGENIERIA_DE_MINAS": 2,
    "FACULTAD_DE_CIENCIAS_BIOLOGICAS": 4,
    "FACULTAD_DE_CIENCIAS_DE_LA_EDUCACION": 5,
    "FACULTAD_DE_INGENIERIA_ESTADISTICA_E_INFORMATICA": 2,
    "FACULTAD_DE_CIENCIAS_JURIDICAS_Y_POLITICAS": 2,
    "FACULTAD_DE_INGENIERIA_QUIMICA": 2,
    "FACULTAD_DE_CIENCIAS_DE_LA_SALUD": 3,
    "FACULTAD_DE_INGENIERIA_GEOLOGICA_Y_METALURGICA": 2,
    "FACULTAD_DE_INGENIERIA_CIVIL_Y_ARQUITECTURA": 3,
    "FACULTAD_DE_INGENIERIA_AGRICOLA": 2,
    "FACULTAD_DE_MEDICINA_HUMANA": 2,
    "FACULTAD_DE_INGENIERIA_MECANICA_ELECTRICA_ELECTRONICA_Y_SISTEMAS": 6,
    "FACULTAD_DE_CIENCIAS_ADMINISTRATIVAS_Y_HUMANAS": 2
  },
  "created_at": "2025-10-31T16:23:03"
}